[{"arguments":["clang","-Wno-documentation-unknown-command","-Wno-unknown-warning-option","-Wno-unknown-pragmas","-nostdinc","-nostdinc++","-g","-std=gnu++1z","-Wall","-Wextra","-Wextra","-fexceptions","-mthreads","-fsyntax-only","-m64","--target=x86_64-w64-mingw32","-DUNICODE","-D_UNICODE","-DWIN32","-DMINGW_HAS_SECURE_API","-DQT_QML_DEBUG","-DQT_WIDGETS_LIB","-DQT_MULTIMEDIA_LIB","-DQT_GUI_LIB","-DQT_NETWORK_LIB","-DQT_SQL_LIB","-DQT_CORE_LIB","-DQT_NEEDS_QMAIN","-DQ_CREATOR_RUN","-DQT_ANNOTATE_FUNCTION(x)=__attribute__((annotate(#x)))","-ID:\\Qt\\Tools\\QtCreator\\share\\qtcreator\\cplusplus\\wrappedMingwHeaders","-ID:\\Qt\\Tools\\QtCreator\\share\\qtcreator\\cplusplus\\wrappedQtHeaders","-ID:\\Qt\\Tools\\QtCreator\\share\\qtcreator\\cplusplus\\wrappedQtHeaders\\QtCore","-ID:\\GitTest\\Bejeweled4","-ID:\\Qt\\6.5.3\\mingw_64\\include","-ID:\\Qt\\6.5.3\\mingw_64\\include\\QtWidgets","-ID:\\Qt\\6.5.3\\mingw_64\\include\\QtMultimedia","-ID:\\Qt\\6.5.3\\mingw_64\\include\\QtGui","-ID:\\Qt\\6.5.3\\mingw_64\\include\\QtNetwork","-ID:\\Qt\\6.5.3\\mingw_64\\include\\QtSql","-ID:\\Qt\\6.5.3\\mingw_64\\include\\QtCore","-ID:\\GitTest\\Bejeweled4\\build\\Desktop_Qt_6_5_3_MinGW_64_bit-Debug\\debug","-ID:\\GitTest\\Bejeweled4\\build\\Desktop_Qt_6_5_3_MinGW_64_bit-Debug","-ID:\\Qt\\6.5.3\\mingw_64\\mkspecs\\win32-g++","-isystem","D:\\Qt\\Tools\\mingw1120_64\\lib\\gcc\\x86_64-w64-mingw32\\11.2.0\\include\\c++","-isystem","D:\\Qt\\Tools\\mingw1120_64\\lib\\gcc\\x86_64-w64-mingw32\\11.2.0\\include\\c++\\x86_64-w64-mingw32","-isystem","D:\\Qt\\Tools\\mingw1120_64\\lib\\gcc\\x86_64-w64-mingw32\\11.2.0\\include\\c++\\backward","-isystem","D:\\Qt\\Tools\\QtCreator\\bin\\clang\\lib\\clang\\18\\include","-isystem","D:\\Qt\\Tools\\mingw1120_64\\x86_64-w64-mingw32\\include","-fmessage-length=0","-fdiagnostics-show-note-include-stack","-fretain-comments-from-system-headers","-fmacro-backtrace-limit=0","-ferror-limit=1000","-x","c++","D:\\GitTest\\Bejeweled4\\Login.cpp"],"directory":"D:/GitTest/Bejeweled4/build/Desktop_Qt_6_5_3_MinGW_64_bit-Debug/.qtc_clangd","file":"D:/GitTest/Bejeweled4/Login.cpp"},{"arguments":["clang","-Wno-documentation-unknown-command","-Wno-unknown-warning-option","-Wno-unknown-pragmas","-nostdinc","-nostdinc++","-g","-std=gnu++1z","-Wall","-Wextra","-Wextra","-fexceptions","-mthreads","-fsyntax-only","-m64","--target=x86_64-w64-mingw32","-DUNICODE","-D_UNICODE","-DWIN32","-DMINGW_HAS_SECURE_API","-DQT_QML_DEBUG","-DQT_WIDGETS_LIB","-DQT_MULTIMEDIA_LIB","-DQT_GUI_LIB","-DQT_NETWORK_LIB","-DQT_SQL_LIB","-DQT_CORE_LIB","-DQT_NEEDS_QMAIN","-DQ_CREATOR_RUN","-DQT_ANNOTATE_FUNCTION(x)=__attribute__((annotate(#x)))","-ID:\\Qt\\Tools\\QtCreator\\share\\qtcreator\\cplusplus\\wrappedMingwHeaders","-ID:\\Qt\\Tools\\QtCreator\\share\\qtcreator\\cplusplus\\wrappedQtHeaders","-ID:\\Qt\\Tools\\QtCreator\\share\\qtcreator\\cplusplus\\wrappedQtHeaders\\QtCore","-ID:\\GitTest\\Bejeweled4","-ID:\\Qt\\6.5.3\\mingw_64\\include","-ID:\\Qt\\6.5.3\\mingw_64\\include\\QtWidgets","-ID:\\Qt\\6.5.3\\mingw_64\\include\\QtMultimedia","-ID:\\Qt\\6.5.3\\mingw_64\\include\\QtGui","-ID:\\Qt\\6.5.3\\mingw_64\\include\\QtNetwork","-ID:\\Qt\\6.5.3\\mingw_64\\include\\QtSql","-ID:\\Qt\\6.5.3\\mingw_64\\include\\QtCore","-ID:\\GitTest\\Bejeweled4\\build\\Desktop_Qt_6_5_3_MinGW_64_bit-Debug\\debug","-ID:\\GitTest\\Bejeweled4\\build\\Desktop_Qt_6_5_3_MinGW_64_bit-Debug","-ID:\\Qt\\6.5.3\\mingw_64\\mkspecs\\win32-g++","-isystem","D:\\Qt\\Tools\\mingw1120_64\\lib\\gcc\\x86_64-w64-mingw32\\11.2.0\\include\\c++","-isystem","D:\\Qt\\Tools\\mingw1120_64\\lib\\gcc\\x86_64-w64-mingw32\\11.2.0\\include\\c++\\x86_64-w64-mingw32","-isystem","D:\\Qt\\Tools\\mingw1120_64\\lib\\gcc\\x86_64-w64-mingw32\\11.2.0\\include\\c++\\backward","-isystem","D:\\Qt\\Tools\\QtCreator\\bin\\clang\\lib\\clang\\18\\include","-isystem","D:\\Qt\\Tools\\mingw1120_64\\x86_64-w64-mingw32\\include","-fmessage-length=0","-fdiagnostics-show-note-include-stack","-fretain-comments-from-system-headers","-fmacro-backtrace-limit=0","-ferror-limit=1000","-x","c++","D:\\GitTest\\Bejeweled4\\PixmapSlider.cpp"],"directory":"D:/GitTest/Bejeweled4/build/Desktop_Qt_6_5_3_MinGW_64_bit-Debug/.qtc_clangd","file":"D:/GitTest/Bejeweled4/PixmapSlider.cpp"},{"arguments":["clang","-Wno-documentation-unknown-command","-Wno-unknown-warning-option","-Wno-unknown-pragmas","-nostdinc","-nostdinc++","-g","-std=gnu++1z","-Wall","-Wextra","-Wextra","-fexceptions","-mthreads","-fsyntax-only","-m64","--target=x86_64-w64-mingw32","-DUNICODE","-D_UNICODE","-DWIN32","-DMINGW_HAS_SECURE_API","-DQT_QML_DEBUG","-DQT_WIDGETS_LIB","-DQT_MULTIMEDIA_LIB","-DQT_GUI_LIB","-DQT_NETWORK_LIB","-DQT_SQL_LIB","-DQT_CORE_LIB","-DQT_NEEDS_QMAIN","-DQ_CREATOR_RUN","-DQT_ANNOTATE_FUNCTION(x)=__attribute__((annotate(#x)))","-ID:\\Qt\\Tools\\QtCreator\\share\\qtcreator\\cplusplus\\wrappedMingwHeaders","-ID:\\Qt\\Tools\\QtCreator\\share\\qtcreator\\cplusplus\\wrappedQtHeaders","-ID:\\Qt\\Tools\\QtCreator\\share\\qtcreator\\cplusplus\\wrappedQtHeaders\\QtCore","-ID:\\GitTest\\Bejeweled4","-ID:\\Qt\\6.5.3\\mingw_64\\include","-ID:\\Qt\\6.5.3\\mingw_64\\include\\QtWidgets","-ID:\\Qt\\6.5.3\\mingw_64\\include\\QtMultimedia","-ID:\\Qt\\6.5.3\\mingw_64\\include\\QtGui","-ID:\\Qt\\6.5.3\\mingw_64\\include\\QtNetwork","-ID:\\Qt\\6.5.3\\mingw_64\\include\\QtSql","-ID:\\Qt\\6.5.3\\mingw_64\\include\\QtCore","-ID:\\GitTest\\Bejeweled4\\build\\Desktop_Qt_6_5_3_MinGW_64_bit-Debug\\debug","-ID:\\GitTest\\Bejeweled4\\build\\Desktop_Qt_6_5_3_MinGW_64_bit-Debug","-ID:\\Qt\\6.5.3\\mingw_64\\mkspecs\\win32-g++","-isystem","D:\\Qt\\Tools\\mingw1120_64\\lib\\gcc\\x86_64-w64-mingw32\\11.2.0\\include\\c++","-isystem","D:\\Qt\\Tools\\mingw1120_64\\lib\\gcc\\x86_64-w64-mingw32\\11.2.0\\include\\c++\\x86_64-w64-mingw32","-isystem","D:\\Qt\\Tools\\mingw1120_64\\lib\\gcc\\x86_64-w64-mingw32\\11.2.0\\include\\c++\\backward","-isystem","D:\\Qt\\Tools\\QtCreator\\bin\\clang\\lib\\clang\\18\\include","-isystem","D:\\Qt\\Tools\\mingw1120_64\\x86_64-w64-mingw32\\include","-fmessage-length=0","-fdiagnostics-show-note-include-stack","-fretain-comments-from-system-headers","-fmacro-backtrace-limit=0","-ferror-limit=1000","-x","c++","D:\\GitTest\\Bejeweled4\\client.cpp"],"directory":"D:/GitTest/Bejeweled4/build/Desktop_Qt_6_5_3_MinGW_64_bit-Debug/.qtc_clangd","file":"D:/GitTest/Bejeweled4/client.cpp"},{"arguments":["clang","-Wno-documentation-unknown-command","-Wno-unknown-warning-option","-Wno-unknown-pragmas","-nostdinc","-nostdinc++","-g","-std=gnu++1z","-Wall","-Wextra","-Wextra","-fexceptions","-mthreads","-fsyntax-only","-m64","--target=x86_64-w64-mingw32","-DUNICODE","-D_UNICODE","-DWIN32","-DMINGW_HAS_SECURE_API","-DQT_QML_DEBUG","-DQT_WIDGETS_LIB","-DQT_MULTIMEDIA_LIB","-DQT_GUI_LIB","-DQT_NETWORK_LIB","-DQT_SQL_LIB","-DQT_CORE_LIB","-DQT_NEEDS_QMAIN","-DQ_CREATOR_RUN","-DQT_ANNOTATE_FUNCTION(x)=__attribute__((annotate(#x)))","-ID:\\Qt\\Tools\\QtCreator\\share\\qtcreator\\cplusplus\\wrappedMingwHeaders","-ID:\\Qt\\Tools\\QtCreator\\share\\qtcreator\\cplusplus\\wrappedQtHeaders","-ID:\\Qt\\Tools\\QtCreator\\share\\qtcreator\\cplusplus\\wrappedQtHeaders\\QtCore","-ID:\\GitTest\\Bejeweled4","-ID:\\Qt\\6.5.3\\mingw_64\\include","-ID:\\Qt\\6.5.3\\mingw_64\\include\\QtWidgets","-ID:\\Qt\\6.5.3\\mingw_64\\include\\QtMultimedia","-ID:\\Qt\\6.5.3\\mingw_64\\include\\QtGui","-ID:\\Qt\\6.5.3\\mingw_64\\include\\QtNetwork","-ID:\\Qt\\6.5.3\\mingw_64\\include\\QtSql","-ID:\\Qt\\6.5.3\\mingw_64\\include\\QtCore","-ID:\\GitTest\\Bejeweled4\\build\\Desktop_Qt_6_5_3_MinGW_64_bit-Debug\\debug","-ID:\\GitTest\\Bejeweled4\\build\\Desktop_Qt_6_5_3_MinGW_64_bit-Debug","-ID:\\Qt\\6.5.3\\mingw_64\\mkspecs\\win32-g++","-isystem","D:\\Qt\\Tools\\mingw1120_64\\lib\\gcc\\x86_64-w64-mingw32\\11.2.0\\include\\c++","-isystem","D:\\Qt\\Tools\\mingw1120_64\\lib\\gcc\\x86_64-w64-mingw32\\11.2.0\\include\\c++\\x86_64-w64-mingw32","-isystem","D:\\Qt\\Tools\\mingw1120_64\\lib\\gcc\\x86_64-w64-mingw32\\11.2.0\\include\\c++\\backward","-isystem","D:\\Qt\\Tools\\QtCreator\\bin\\clang\\lib\\clang\\18\\include","-isystem","D:\\Qt\\Tools\\mingw1120_64\\x86_64-w64-mingw32\\include","-fmessage-length=0","-fdiagnostics-show-note-include-stack","-fretain-comments-from-system-headers","-fmacro-backtrace-limit=0","-ferror-limit=1000","-x","c++","D:\\GitTest\\Bejeweled4\\end.cpp"],"directory":"D:/GitTest/Bejeweled4/build/Desktop_Qt_6_5_3_MinGW_64_bit-Debug/.qtc_clangd","file":"D:/GitTest/Bejeweled4/end.cpp"},{"arguments":["clang","-Wno-documentation-unknown-command","-Wno-unknown-warning-option","-Wno-unknown-pragmas","-nostdinc","-nostdinc++","-g","-std=gnu++1z","-Wall","-Wextra","-Wextra","-fexceptions","-mthreads","-fsyntax-only","-m64","--target=x86_64-w64-mingw32","-DUNICODE","-D_UNICODE","-DWIN32","-DMINGW_HAS_SECURE_API","-DQT_QML_DEBUG","-DQT_WIDGETS_LIB","-DQT_MULTIMEDIA_LIB","-DQT_GUI_LIB","-DQT_NETWORK_LIB","-DQT_SQL_LIB","-DQT_CORE_LIB","-DQT_NEEDS_QMAIN","-DQ_CREATOR_RUN","-DQT_ANNOTATE_FUNCTION(x)=__attribute__((annotate(#x)))","-ID:\\Qt\\Tools\\QtCreator\\share\\qtcreator\\cplusplus\\wrappedMingwHeaders","-ID:\\Qt\\Tools\\QtCreator\\share\\qtcreator\\cplusplus\\wrappedQtHeaders","-ID:\\Qt\\Tools\\QtCreator\\share\\qtcreator\\cplusplus\\wrappedQtHeaders\\QtCore","-ID:\\GitTest\\Bejeweled4","-ID:\\Qt\\6.5.3\\mingw_64\\include","-ID:\\Qt\\6.5.3\\mingw_64\\include\\QtWidgets","-ID:\\Qt\\6.5.3\\mingw_64\\include\\QtMultimedia","-ID:\\Qt\\6.5.3\\mingw_64\\include\\QtGui","-ID:\\Qt\\6.5.3\\mingw_64\\include\\QtNetwork","-ID:\\Qt\\6.5.3\\mingw_64\\include\\QtSql","-ID:\\Qt\\6.5.3\\mingw_64\\include\\QtCore","-ID:\\GitTest\\Bejeweled4\\build\\Desktop_Qt_6_5_3_MinGW_64_bit-Debug\\debug","-ID:\\GitTest\\Bejeweled4\\build\\Desktop_Qt_6_5_3_MinGW_64_bit-Debug","-ID:\\Qt\\6.5.3\\mingw_64\\mkspecs\\win32-g++","-isystem","D:\\Qt\\Tools\\mingw1120_64\\lib\\gcc\\x86_64-w64-mingw32\\11.2.0\\include\\c++","-isystem","D:\\Qt\\Tools\\mingw1120_64\\lib\\gcc\\x86_64-w64-mingw32\\11.2.0\\include\\c++\\x86_64-w64-mingw32","-isystem","D:\\Qt\\Tools\\mingw1120_64\\lib\\gcc\\x86_64-w64-mingw32\\11.2.0\\include\\c++\\backward","-isystem","D:\\Qt\\Tools\\QtCreator\\bin\\clang\\lib\\clang\\18\\include","-isystem","D:\\Qt\\Tools\\mingw1120_64\\x86_64-w64-mingw32\\include","-fmessage-length=0","-fdiagnostics-show-note-include-stack","-fretain-comments-from-system-headers","-fmacro-backtrace-limit=0","-ferror-limit=1000","-x","c++","D:\\GitTest\\Bejeweled4\\game.cpp"],"directory":"D:/GitTest/Bejeweled4/build/Desktop_Qt_6_5_3_MinGW_64_bit-Debug/.qtc_clangd","file":"D:/GitTest/Bejeweled4/game.cpp"},{"arguments":["clang","-Wno-documentation-unknown-command","-Wno-unknown-warning-option","-Wno-unknown-pragmas","-nostdinc","-nostdinc++","-g","-std=gnu++1z","-Wall","-Wextra","-Wextra","-fexceptions","-mthreads","-fsyntax-only","-m64","--target=x86_64-w64-mingw32","-DUNICODE","-D_UNICODE","-DWIN32","-DMINGW_HAS_SECURE_API","-DQT_QML_DEBUG","-DQT_WIDGETS_LIB","-DQT_MULTIMEDIA_LIB","-DQT_GUI_LIB","-DQT_NETWORK_LIB","-DQT_SQL_LIB","-DQT_CORE_LIB","-DQT_NEEDS_QMAIN","-DQ_CREATOR_RUN","-DQT_ANNOTATE_FUNCTION(x)=__attribute__((annotate(#x)))","-ID:\\Qt\\Tools\\QtCreator\\share\\qtcreator\\cplusplus\\wrappedMingwHeaders","-ID:\\Qt\\Tools\\QtCreator\\share\\qtcreator\\cplusplus\\wrappedQtHeaders","-ID:\\Qt\\Tools\\QtCreator\\share\\qtcreator\\cplusplus\\wrappedQtHeaders\\QtCore","-ID:\\GitTest\\Bejeweled4","-ID:\\Qt\\6.5.3\\mingw_64\\include","-ID:\\Qt\\6.5.3\\mingw_64\\include\\QtWidgets","-ID:\\Qt\\6.5.3\\mingw_64\\include\\QtMultimedia","-ID:\\Qt\\6.5.3\\mingw_64\\include\\QtGui","-ID:\\Qt\\6.5.3\\mingw_64\\include\\QtNetwork","-ID:\\Qt\\6.5.3\\mingw_64\\include\\QtSql","-ID:\\Qt\\6.5.3\\mingw_64\\include\\QtCore","-ID:\\GitTest\\Bejeweled4\\build\\Desktop_Qt_6_5_3_MinGW_64_bit-Debug\\debug","-ID:\\GitTest\\Bejeweled4\\build\\Desktop_Qt_6_5_3_MinGW_64_bit-Debug","-ID:\\Qt\\6.5.3\\mingw_64\\mkspecs\\win32-g++","-isystem","D:\\Qt\\Tools\\mingw1120_64\\lib\\gcc\\x86_64-w64-mingw32\\11.2.0\\include\\c++","-isystem","D:\\Qt\\Tools\\mingw1120_64\\lib\\gcc\\x86_64-w64-mingw32\\11.2.0\\include\\c++\\x86_64-w64-mingw32","-isystem","D:\\Qt\\Tools\\mingw1120_64\\lib\\gcc\\x86_64-w64-mingw32\\11.2.0\\include\\c++\\backward","-isystem","D:\\Qt\\Tools\\QtCreator\\bin\\clang\\lib\\clang\\18\\include","-isystem","D:\\Qt\\Tools\\mingw1120_64\\x86_64-w64-mingw32\\include","-fmessage-length=0","-fdiagnostics-show-note-include-stack","-fretain-comments-from-system-headers","-fmacro-backtrace-limit=0","-ferror-limit=1000","-x","c++","D:\\GitTest\\Bejeweled4\\gametimer.cpp"],"directory":"D:/GitTest/Bejeweled4/build/Desktop_Qt_6_5_3_MinGW_64_bit-Debug/.qtc_clangd","file":"D:/GitTest/Bejeweled4/gametimer.cpp"},{"arguments":["clang","-Wno-documentation-unknown-command","-Wno-unknown-warning-option","-Wno-unknown-pragmas","-nostdinc","-nostdinc++","-g","-std=gnu++1z","-Wall","-Wextra","-Wextra","-fexceptions","-mthreads","-fsyntax-only","-m64","--target=x86_64-w64-mingw32","-DUNICODE","-D_UNICODE","-DWIN32","-DMINGW_HAS_SECURE_API","-DQT_QML_DEBUG","-DQT_WIDGETS_LIB","-DQT_MULTIMEDIA_LIB","-DQT_GUI_LIB","-DQT_NETWORK_LIB","-DQT_SQL_LIB","-DQT_CORE_LIB","-DQT_NEEDS_QMAIN","-DQ_CREATOR_RUN","-DQT_ANNOTATE_FUNCTION(x)=__attribute__((annotate(#x)))","-ID:\\Qt\\Tools\\QtCreator\\share\\qtcreator\\cplusplus\\wrappedMingwHeaders","-ID:\\Qt\\Tools\\QtCreator\\share\\qtcreator\\cplusplus\\wrappedQtHeaders","-ID:\\Qt\\Tools\\QtCreator\\share\\qtcreator\\cplusplus\\wrappedQtHeaders\\QtCore","-ID:\\GitTest\\Bejeweled4","-ID:\\Qt\\6.5.3\\mingw_64\\include","-ID:\\Qt\\6.5.3\\mingw_64\\include\\QtWidgets","-ID:\\Qt\\6.5.3\\mingw_64\\include\\QtMultimedia","-ID:\\Qt\\6.5.3\\mingw_64\\include\\QtGui","-ID:\\Qt\\6.5.3\\mingw_64\\include\\QtNetwork","-ID:\\Qt\\6.5.3\\mingw_64\\include\\QtSql","-ID:\\Qt\\6.5.3\\mingw_64\\include\\QtCore","-ID:\\GitTest\\Bejeweled4\\build\\Desktop_Qt_6_5_3_MinGW_64_bit-Debug\\debug","-ID:\\GitTest\\Bejeweled4\\build\\Desktop_Qt_6_5_3_MinGW_64_bit-Debug","-ID:\\Qt\\6.5.3\\mingw_64\\mkspecs\\win32-g++","-isystem","D:\\Qt\\Tools\\mingw1120_64\\lib\\gcc\\x86_64-w64-mingw32\\11.2.0\\include\\c++","-isystem","D:\\Qt\\Tools\\mingw1120_64\\lib\\gcc\\x86_64-w64-mingw32\\11.2.0\\include\\c++\\x86_64-w64-mingw32","-isystem","D:\\Qt\\Tools\\mingw1120_64\\lib\\gcc\\x86_64-w64-mingw32\\11.2.0\\include\\c++\\backward","-isystem","D:\\Qt\\Tools\\QtCreator\\bin\\clang\\lib\\clang\\18\\include","-isystem","D:\\Qt\\Tools\\mingw1120_64\\x86_64-w64-mingw32\\include","-fmessage-length=0","-fdiagnostics-show-note-include-stack","-fretain-comments-from-system-headers","-fmacro-backtrace-limit=0","-ferror-limit=1000","-x","c++","D:\\GitTest\\Bejeweled4\\globalvalue.cpp"],"directory":"D:/GitTest/Bejeweled4/build/Desktop_Qt_6_5_3_MinGW_64_bit-Debug/.qtc_clangd","file":"D:/GitTest/Bejeweled4/globalvalue.cpp"},{"arguments":["clang","-Wno-documentation-unknown-command","-Wno-unknown-warning-option","-Wno-unknown-pragmas","-nostdinc","-nostdinc++","-g","-std=gnu++1z","-Wall","-Wextra","-Wextra","-fexceptions","-mthreads","-fsyntax-only","-m64","--target=x86_64-w64-mingw32","-DUNICODE","-D_UNICODE","-DWIN32","-DMINGW_HAS_SECURE_API","-DQT_QML_DEBUG","-DQT_WIDGETS_LIB","-DQT_MULTIMEDIA_LIB","-DQT_GUI_LIB","-DQT_NETWORK_LIB","-DQT_SQL_LIB","-DQT_CORE_LIB","-DQT_NEEDS_QMAIN","-DQ_CREATOR_RUN","-DQT_ANNOTATE_FUNCTION(x)=__attribute__((annotate(#x)))","-ID:\\Qt\\Tools\\QtCreator\\share\\qtcreator\\cplusplus\\wrappedMingwHeaders","-ID:\\Qt\\Tools\\QtCreator\\share\\qtcreator\\cplusplus\\wrappedQtHeaders","-ID:\\Qt\\Tools\\QtCreator\\share\\qtcreator\\cplusplus\\wrappedQtHeaders\\QtCore","-ID:\\GitTest\\Bejeweled4","-ID:\\Qt\\6.5.3\\mingw_64\\include","-ID:\\Qt\\6.5.3\\mingw_64\\include\\QtWidgets","-ID:\\Qt\\6.5.3\\mingw_64\\include\\QtMultimedia","-ID:\\Qt\\6.5.3\\mingw_64\\include\\QtGui","-ID:\\Qt\\6.5.3\\mingw_64\\include\\QtNetwork","-ID:\\Qt\\6.5.3\\mingw_64\\include\\QtSql","-ID:\\Qt\\6.5.3\\mingw_64\\include\\QtCore","-ID:\\GitTest\\Bejeweled4\\build\\Desktop_Qt_6_5_3_MinGW_64_bit-Debug\\debug","-ID:\\GitTest\\Bejeweled4\\build\\Desktop_Qt_6_5_3_MinGW_64_bit-Debug","-ID:\\Qt\\6.5.3\\mingw_64\\mkspecs\\win32-g++","-isystem","D:\\Qt\\Tools\\mingw1120_64\\lib\\gcc\\x86_64-w64-mingw32\\11.2.0\\include\\c++","-isystem","D:\\Qt\\Tools\\mingw1120_64\\lib\\gcc\\x86_64-w64-mingw32\\11.2.0\\include\\c++\\x86_64-w64-mingw32","-isystem","D:\\Qt\\Tools\\mingw1120_64\\lib\\gcc\\x86_64-w64-mingw32\\11.2.0\\include\\c++\\backward","-isystem","D:\\Qt\\Tools\\QtCreator\\bin\\clang\\lib\\clang\\18\\include","-isystem","D:\\Qt\\Tools\\mingw1120_64\\x86_64-w64-mingw32\\include","-fmessage-length=0","-fdiagnostics-show-note-include-stack","-fretain-comments-from-system-headers","-fmacro-backtrace-limit=0","-ferror-limit=1000","-x","c++","D:\\GitTest\\Bejeweled4\\hoverbutton.cpp"],"directory":"D:/GitTest/Bejeweled4/build/Desktop_Qt_6_5_3_MinGW_64_bit-Debug/.qtc_clangd","file":"D:/GitTest/Bejeweled4/hoverbutton.cpp"},{"arguments":["clang","-Wno-documentation-unknown-command","-Wno-unknown-warning-option","-Wno-unknown-pragmas","-nostdinc","-nostdinc++","-g","-std=gnu++1z","-Wall","-Wextra","-Wextra","-fexceptions","-mthreads","-fsyntax-only","-m64","--target=x86_64-w64-mingw32","-DUNICODE","-D_UNICODE","-DWIN32","-DMINGW_HAS_SECURE_API","-DQT_QML_DEBUG","-DQT_WIDGETS_LIB","-DQT_MULTIMEDIA_LIB","-DQT_GUI_LIB","-DQT_NETWORK_LIB","-DQT_SQL_LIB","-DQT_CORE_LIB","-DQT_NEEDS_QMAIN","-DQ_CREATOR_RUN","-DQT_ANNOTATE_FUNCTION(x)=__attribute__((annotate(#x)))","-ID:\\Qt\\Tools\\QtCreator\\share\\qtcreator\\cplusplus\\wrappedMingwHeaders","-ID:\\Qt\\Tools\\QtCreator\\share\\qtcreator\\cplusplus\\wrappedQtHeaders","-ID:\\Qt\\Tools\\QtCreator\\share\\qtcreator\\cplusplus\\wrappedQtHeaders\\QtCore","-ID:\\GitTest\\Bejeweled4","-ID:\\Qt\\6.5.3\\mingw_64\\include","-ID:\\Qt\\6.5.3\\mingw_64\\include\\QtWidgets","-ID:\\Qt\\6.5.3\\mingw_64\\include\\QtMultimedia","-ID:\\Qt\\6.5.3\\mingw_64\\include\\QtGui","-ID:\\Qt\\6.5.3\\mingw_64\\include\\QtNetwork","-ID:\\Qt\\6.5.3\\mingw_64\\include\\QtSql","-ID:\\Qt\\6.5.3\\mingw_64\\include\\QtCore","-ID:\\GitTest\\Bejeweled4\\build\\Desktop_Qt_6_5_3_MinGW_64_bit-Debug\\debug","-ID:\\GitTest\\Bejeweled4\\build\\Desktop_Qt_6_5_3_MinGW_64_bit-Debug","-ID:\\Qt\\6.5.3\\mingw_64\\mkspecs\\win32-g++","-isystem","D:\\Qt\\Tools\\mingw1120_64\\lib\\gcc\\x86_64-w64-mingw32\\11.2.0\\include\\c++","-isystem","D:\\Qt\\Tools\\mingw1120_64\\lib\\gcc\\x86_64-w64-mingw32\\11.2.0\\include\\c++\\x86_64-w64-mingw32","-isystem","D:\\Qt\\Tools\\mingw1120_64\\lib\\gcc\\x86_64-w64-mingw32\\11.2.0\\include\\c++\\backward","-isystem","D:\\Qt\\Tools\\QtCreator\\bin\\clang\\lib\\clang\\18\\include","-isystem","D:\\Qt\\Tools\\mingw1120_64\\x86_64-w64-mingw32\\include","-fmessage-length=0","-fdiagnostics-show-note-include-stack","-fretain-comments-from-system-headers","-fmacro-backtrace-limit=0","-ferror-limit=1000","-x","c++","D:\\GitTest\\Bejeweled4\\main.cpp"],"directory":"D:/GitTest/Bejeweled4/build/Desktop_Qt_6_5_3_MinGW_64_bit-Debug/.qtc_clangd","file":"D:/GitTest/Bejeweled4/main.cpp"},{"arguments":["clang","-Wno-documentation-unknown-command","-Wno-unknown-warning-option","-Wno-unknown-pragmas","-nostdinc","-nostdinc++","-g","-std=gnu++1z","-Wall","-Wextra","-Wextra","-fexceptions","-mthreads","-fsyntax-only","-m64","--target=x86_64-w64-mingw32","-DUNICODE","-D_UNICODE","-DWIN32","-DMINGW_HAS_SECURE_API","-DQT_QML_DEBUG","-DQT_WIDGETS_LIB","-DQT_MULTIMEDIA_LIB","-DQT_GUI_LIB","-DQT_NETWORK_LIB","-DQT_SQL_LIB","-DQT_CORE_LIB","-DQT_NEEDS_QMAIN","-DQ_CREATOR_RUN","-DQT_ANNOTATE_FUNCTION(x)=__attribute__((annotate(#x)))","-ID:\\Qt\\Tools\\QtCreator\\share\\qtcreator\\cplusplus\\wrappedMingwHeaders","-ID:\\Qt\\Tools\\QtCreator\\share\\qtcreator\\cplusplus\\wrappedQtHeaders","-ID:\\Qt\\Tools\\QtCreator\\share\\qtcreator\\cplusplus\\wrappedQtHeaders\\QtCore","-ID:\\GitTest\\Bejeweled4","-ID:\\Qt\\6.5.3\\mingw_64\\include","-ID:\\Qt\\6.5.3\\mingw_64\\include\\QtWidgets","-ID:\\Qt\\6.5.3\\mingw_64\\include\\QtMultimedia","-ID:\\Qt\\6.5.3\\mingw_64\\include\\QtGui","-ID:\\Qt\\6.5.3\\mingw_64\\include\\QtNetwork","-ID:\\Qt\\6.5.3\\mingw_64\\include\\QtSql","-ID:\\Qt\\6.5.3\\mingw_64\\include\\QtCore","-ID:\\GitTest\\Bejeweled4\\build\\Desktop_Qt_6_5_3_MinGW_64_bit-Debug\\debug","-ID:\\GitTest\\Bejeweled4\\build\\Desktop_Qt_6_5_3_MinGW_64_bit-Debug","-ID:\\Qt\\6.5.3\\mingw_64\\mkspecs\\win32-g++","-isystem","D:\\Qt\\Tools\\mingw1120_64\\lib\\gcc\\x86_64-w64-mingw32\\11.2.0\\include\\c++","-isystem","D:\\Qt\\Tools\\mingw1120_64\\lib\\gcc\\x86_64-w64-mingw32\\11.2.0\\include\\c++\\x86_64-w64-mingw32","-isystem","D:\\Qt\\Tools\\mingw1120_64\\lib\\gcc\\x86_64-w64-mingw32\\11.2.0\\include\\c++\\backward","-isystem","D:\\Qt\\Tools\\QtCreator\\bin\\clang\\lib\\clang\\18\\include","-isystem","D:\\Qt\\Tools\\mingw1120_64\\x86_64-w64-mingw32\\include","-fmessage-length=0","-fdiagnostics-show-note-include-stack","-fretain-comments-from-system-headers","-fmacro-backtrace-limit=0","-ferror-limit=1000","-x","c++","D:\\GitTest\\Bejeweled4\\mainwindow.cpp"],"directory":"D:/GitTest/Bejeweled4/build/Desktop_Qt_6_5_3_MinGW_64_bit-Debug/.qtc_clangd","file":"D:/GitTest/Bejeweled4/mainwindow.cpp"},{"arguments":["clang","-Wno-documentation-unknown-command","-Wno-unknown-warning-option","-Wno-unknown-pragmas","-nostdinc","-nostdinc++","-g","-std=gnu++1z","-Wall","-Wextra","-Wextra","-fexceptions","-mthreads","-fsyntax-only","-m64","--target=x86_64-w64-mingw32","-DUNICODE","-D_UNICODE","-DWIN32","-DMINGW_HAS_SECURE_API","-DQT_QML_DEBUG","-DQT_WIDGETS_LIB","-DQT_MULTIMEDIA_LIB","-DQT_GUI_LIB","-DQT_NETWORK_LIB","-DQT_SQL_LIB","-DQT_CORE_LIB","-DQT_NEEDS_QMAIN","-DQ_CREATOR_RUN","-DQT_ANNOTATE_FUNCTION(x)=__attribute__((annotate(#x)))","-ID:\\Qt\\Tools\\QtCreator\\share\\qtcreator\\cplusplus\\wrappedMingwHeaders","-ID:\\Qt\\Tools\\QtCreator\\share\\qtcreator\\cplusplus\\wrappedQtHeaders","-ID:\\Qt\\Tools\\QtCreator\\share\\qtcreator\\cplusplus\\wrappedQtHeaders\\QtCore","-ID:\\GitTest\\Bejeweled4","-ID:\\Qt\\6.5.3\\mingw_64\\include","-ID:\\Qt\\6.5.3\\mingw_64\\include\\QtWidgets","-ID:\\Qt\\6.5.3\\mingw_64\\include\\QtMultimedia","-ID:\\Qt\\6.5.3\\mingw_64\\include\\QtGui","-ID:\\Qt\\6.5.3\\mingw_64\\include\\QtNetwork","-ID:\\Qt\\6.5.3\\mingw_64\\include\\QtSql","-ID:\\Qt\\6.5.3\\mingw_64\\include\\QtCore","-ID:\\GitTest\\Bejeweled4\\build\\Desktop_Qt_6_5_3_MinGW_64_bit-Debug\\debug","-ID:\\GitTest\\Bejeweled4\\build\\Desktop_Qt_6_5_3_MinGW_64_bit-Debug","-ID:\\Qt\\6.5.3\\mingw_64\\mkspecs\\win32-g++","-isystem","D:\\Qt\\Tools\\mingw1120_64\\lib\\gcc\\x86_64-w64-mingw32\\11.2.0\\include\\c++","-isystem","D:\\Qt\\Tools\\mingw1120_64\\lib\\gcc\\x86_64-w64-mingw32\\11.2.0\\include\\c++\\x86_64-w64-mingw32","-isystem","D:\\Qt\\Tools\\mingw1120_64\\lib\\gcc\\x86_64-w64-mingw32\\11.2.0\\include\\c++\\backward","-isystem","D:\\Qt\\Tools\\QtCreator\\bin\\clang\\lib\\clang\\18\\include","-isystem","D:\\Qt\\Tools\\mingw1120_64\\x86_64-w64-mingw32\\include","-fmessage-length=0","-fdiagnostics-show-note-include-stack","-fretain-comments-from-system-headers","-fmacro-backtrace-limit=0","-ferror-limit=1000","-x","c++","D:\\GitTest\\Bejeweled4\\rankdialog.cpp"],"directory":"D:/GitTest/Bejeweled4/build/Desktop_Qt_6_5_3_MinGW_64_bit-Debug/.qtc_clangd","file":"D:/GitTest/Bejeweled4/rankdialog.cpp"},{"arguments":["clang","-Wno-documentation-unknown-command","-Wno-unknown-warning-option","-Wno-unknown-pragmas","-nostdinc","-nostdinc++","-g","-std=gnu++1z","-Wall","-Wextra","-Wextra","-fexceptions","-mthreads","-fsyntax-only","-m64","--target=x86_64-w64-mingw32","-DUNICODE","-D_UNICODE","-DWIN32","-DMINGW_HAS_SECURE_API","-DQT_QML_DEBUG","-DQT_WIDGETS_LIB","-DQT_MULTIMEDIA_LIB","-DQT_GUI_LIB","-DQT_NETWORK_LIB","-DQT_SQL_LIB","-DQT_CORE_LIB","-DQT_NEEDS_QMAIN","-DQ_CREATOR_RUN","-DQT_ANNOTATE_FUNCTION(x)=__attribute__((annotate(#x)))","-ID:\\Qt\\Tools\\QtCreator\\share\\qtcreator\\cplusplus\\wrappedMingwHeaders","-ID:\\Qt\\Tools\\QtCreator\\share\\qtcreator\\cplusplus\\wrappedQtHeaders","-ID:\\Qt\\Tools\\QtCreator\\share\\qtcreator\\cplusplus\\wrappedQtHeaders\\QtCore","-ID:\\GitTest\\Bejeweled4","-ID:\\Qt\\6.5.3\\mingw_64\\include","-ID:\\Qt\\6.5.3\\mingw_64\\include\\QtWidgets","-ID:\\Qt\\6.5.3\\mingw_64\\include\\QtMultimedia","-ID:\\Qt\\6.5.3\\mingw_64\\include\\QtGui","-ID:\\Qt\\6.5.3\\mingw_64\\include\\QtNetwork","-ID:\\Qt\\6.5.3\\mingw_64\\include\\QtSql","-ID:\\Qt\\6.5.3\\mingw_64\\include\\QtCore","-ID:\\GitTest\\Bejeweled4\\build\\Desktop_Qt_6_5_3_MinGW_64_bit-Debug\\debug","-ID:\\GitTest\\Bejeweled4\\build\\Desktop_Qt_6_5_3_MinGW_64_bit-Debug","-ID:\\Qt\\6.5.3\\mingw_64\\mkspecs\\win32-g++","-isystem","D:\\Qt\\Tools\\mingw1120_64\\lib\\gcc\\x86_64-w64-mingw32\\11.2.0\\include\\c++","-isystem","D:\\Qt\\Tools\\mingw1120_64\\lib\\gcc\\x86_64-w64-mingw32\\11.2.0\\include\\c++\\x86_64-w64-mingw32","-isystem","D:\\Qt\\Tools\\mingw1120_64\\lib\\gcc\\x86_64-w64-mingw32\\11.2.0\\include\\c++\\backward","-isystem","D:\\Qt\\Tools\\QtCreator\\bin\\clang\\lib\\clang\\18\\include","-isystem","D:\\Qt\\Tools\\mingw1120_64\\x86_64-w64-mingw32\\include","-fmessage-length=0","-fdiagnostics-show-note-include-stack","-fretain-comments-from-system-headers","-fmacro-backtrace-limit=0","-ferror-limit=1000","-x","c++","D:\\GitTest\\Bejeweled4\\settingwidget.cpp"],"directory":"D:/GitTest/Bejeweled4/build/Desktop_Qt_6_5_3_MinGW_64_bit-Debug/.qtc_clangd","file":"D:/GitTest/Bejeweled4/settingwidget.cpp"},{"arguments":["clang","-Wno-documentation-unknown-command","-Wno-unknown-warning-option","-Wno-unknown-pragmas","-nostdinc","-nostdinc++","-g","-std=gnu++1z","-Wall","-Wextra","-Wextra","-fexceptions","-mthreads","-fsyntax-only","-m64","--target=x86_64-w64-mingw32","-DUNICODE","-D_UNICODE","-DWIN32","-DMINGW_HAS_SECURE_API","-DQT_QML_DEBUG","-DQT_WIDGETS_LIB","-DQT_MULTIMEDIA_LIB","-DQT_GUI_LIB","-DQT_NETWORK_LIB","-DQT_SQL_LIB","-DQT_CORE_LIB","-DQT_NEEDS_QMAIN","-DQ_CREATOR_RUN","-DQT_ANNOTATE_FUNCTION(x)=__attribute__((annotate(#x)))","-ID:\\Qt\\Tools\\QtCreator\\share\\qtcreator\\cplusplus\\wrappedMingwHeaders","-ID:\\Qt\\Tools\\QtCreator\\share\\qtcreator\\cplusplus\\wrappedQtHeaders","-ID:\\Qt\\Tools\\QtCreator\\share\\qtcreator\\cplusplus\\wrappedQtHeaders\\QtCore","-ID:\\GitTest\\Bejeweled4","-ID:\\Qt\\6.5.3\\mingw_64\\include","-ID:\\Qt\\6.5.3\\mingw_64\\include\\QtWidgets","-ID:\\Qt\\6.5.3\\mingw_64\\include\\QtMultimedia","-ID:\\Qt\\6.5.3\\mingw_64\\include\\QtGui","-ID:\\Qt\\6.5.3\\mingw_64\\include\\QtNetwork","-ID:\\Qt\\6.5.3\\mingw_64\\include\\QtSql","-ID:\\Qt\\6.5.3\\mingw_64\\include\\QtCore","-ID:\\GitTest\\Bejeweled4\\build\\Desktop_Qt_6_5_3_MinGW_64_bit-Debug\\debug","-ID:\\GitTest\\Bejeweled4\\build\\Desktop_Qt_6_5_3_MinGW_64_bit-Debug","-ID:\\Qt\\6.5.3\\mingw_64\\mkspecs\\win32-g++","-isystem","D:\\Qt\\Tools\\mingw1120_64\\lib\\gcc\\x86_64-w64-mingw32\\11.2.0\\include\\c++","-isystem","D:\\Qt\\Tools\\mingw1120_64\\lib\\gcc\\x86_64-w64-mingw32\\11.2.0\\include\\c++\\x86_64-w64-mingw32","-isystem","D:\\Qt\\Tools\\mingw1120_64\\lib\\gcc\\x86_64-w64-mingw32\\11.2.0\\include\\c++\\backward","-isystem","D:\\Qt\\Tools\\QtCreator\\bin\\clang\\lib\\clang\\18\\include","-isystem","D:\\Qt\\Tools\\mingw1120_64\\x86_64-w64-mingw32\\include","-fmessage-length=0","-fdiagnostics-show-note-include-stack","-fretain-comments-from-system-headers","-fmacro-backtrace-limit=0","-ferror-limit=1000","-x","c++","D:\\GitTest\\Bejeweled4\\pause.cpp"],"directory":"D:/GitTest/Bejeweled4/build/Desktop_Qt_6_5_3_MinGW_64_bit-Debug/.qtc_clangd","file":"D:/GitTest/Bejeweled4/pause.cpp"},{"arguments":["clang","-Wno-documentation-unknown-command","-Wno-unknown-warning-option","-Wno-unknown-pragmas","-nostdinc","-nostdinc++","-g","-std=gnu++1z","-Wall","-Wextra","-Wextra","-fexceptions","-mthreads","-fsyntax-only","-m64","--target=x86_64-w64-mingw32","-DUNICODE","-D_UNICODE","-DWIN32","-DMINGW_HAS_SECURE_API","-DQT_QML_DEBUG","-DQT_WIDGETS_LIB","-DQT_MULTIMEDIA_LIB","-DQT_GUI_LIB","-DQT_NETWORK_LIB","-DQT_SQL_LIB","-DQT_CORE_LIB","-DQT_NEEDS_QMAIN","-DQ_CREATOR_RUN","-DQT_ANNOTATE_FUNCTION(x)=__attribute__((annotate(#x)))","-ID:\\Qt\\Tools\\QtCreator\\share\\qtcreator\\cplusplus\\wrappedMingwHeaders","-ID:\\Qt\\Tools\\QtCreator\\share\\qtcreator\\cplusplus\\wrappedQtHeaders","-ID:\\Qt\\Tools\\QtCreator\\share\\qtcreator\\cplusplus\\wrappedQtHeaders\\QtCore","-ID:\\GitTest\\Bejeweled4","-ID:\\Qt\\6.5.3\\mingw_64\\include","-ID:\\Qt\\6.5.3\\mingw_64\\include\\QtWidgets","-ID:\\Qt\\6.5.3\\mingw_64\\include\\QtMultimedia","-ID:\\Qt\\6.5.3\\mingw_64\\include\\QtGui","-ID:\\Qt\\6.5.3\\mingw_64\\include\\QtNetwork","-ID:\\Qt\\6.5.3\\mingw_64\\include\\QtSql","-ID:\\Qt\\6.5.3\\mingw_64\\include\\QtCore","-ID:\\GitTest\\Bejeweled4\\build\\Desktop_Qt_6_5_3_MinGW_64_bit-Debug\\debug","-ID:\\GitTest\\Bejeweled4\\build\\Desktop_Qt_6_5_3_MinGW_64_bit-Debug","-ID:\\Qt\\6.5.3\\mingw_64\\mkspecs\\win32-g++","-isystem","D:\\Qt\\Tools\\mingw1120_64\\lib\\gcc\\x86_64-w64-mingw32\\11.2.0\\include\\c++","-isystem","D:\\Qt\\Tools\\mingw1120_64\\lib\\gcc\\x86_64-w64-mingw32\\11.2.0\\include\\c++\\x86_64-w64-mingw32","-isystem","D:\\Qt\\Tools\\mingw1120_64\\lib\\gcc\\x86_64-w64-mingw32\\11.2.0\\include\\c++\\backward","-isystem","D:\\Qt\\Tools\\QtCreator\\bin\\clang\\lib\\clang\\18\\include","-isystem","D:\\Qt\\Tools\\mingw1120_64\\x86_64-w64-mingw32\\include","-fmessage-length=0","-fdiagnostics-show-note-include-stack","-fretain-comments-from-system-headers","-fmacro-backtrace-limit=0","-ferror-limit=1000","-x","c++","D:\\GitTest\\Bejeweled4\\shopwidget.cpp"],"directory":"D:/GitTest/Bejeweled4/build/Desktop_Qt_6_5_3_MinGW_64_bit-Debug/.qtc_clangd","file":"D:/GitTest/Bejeweled4/shopwidget.cpp"},{"arguments":["clang","-Wno-documentation-unknown-command","-Wno-unknown-warning-option","-Wno-unknown-pragmas","-nostdinc","-nostdinc++","-g","-std=gnu++1z","-Wall","-Wextra","-Wextra","-fexceptions","-mthreads","-fsyntax-only","-m64","--target=x86_64-w64-mingw32","-DUNICODE","-D_UNICODE","-DWIN32","-DMINGW_HAS_SECURE_API","-DQT_QML_DEBUG","-DQT_WIDGETS_LIB","-DQT_MULTIMEDIA_LIB","-DQT_GUI_LIB","-DQT_NETWORK_LIB","-DQT_SQL_LIB","-DQT_CORE_LIB","-DQT_NEEDS_QMAIN","-DQ_CREATOR_RUN","-DQT_ANNOTATE_FUNCTION(x)=__attribute__((annotate(#x)))","-ID:\\Qt\\Tools\\QtCreator\\share\\qtcreator\\cplusplus\\wrappedMingwHeaders","-ID:\\Qt\\Tools\\QtCreator\\share\\qtcreator\\cplusplus\\wrappedQtHeaders","-ID:\\Qt\\Tools\\QtCreator\\share\\qtcreator\\cplusplus\\wrappedQtHeaders\\QtCore","-ID:\\GitTest\\Bejeweled4","-ID:\\Qt\\6.5.3\\mingw_64\\include","-ID:\\Qt\\6.5.3\\mingw_64\\include\\QtWidgets","-ID:\\Qt\\6.5.3\\mingw_64\\include\\QtMultimedia","-ID:\\Qt\\6.5.3\\mingw_64\\include\\QtGui","-ID:\\Qt\\6.5.3\\mingw_64\\include\\QtNetwork","-ID:\\Qt\\6.5.3\\mingw_64\\include\\QtSql","-ID:\\Qt\\6.5.3\\mingw_64\\include\\QtCore","-ID:\\GitTest\\Bejeweled4\\build\\Desktop_Qt_6_5_3_MinGW_64_bit-Debug\\debug","-ID:\\GitTest\\Bejeweled4\\build\\Desktop_Qt_6_5_3_MinGW_64_bit-Debug","-ID:\\Qt\\6.5.3\\mingw_64\\mkspecs\\win32-g++","-isystem","D:\\Qt\\Tools\\mingw1120_64\\lib\\gcc\\x86_64-w64-mingw32\\11.2.0\\include\\c++","-isystem","D:\\Qt\\Tools\\mingw1120_64\\lib\\gcc\\x86_64-w64-mingw32\\11.2.0\\include\\c++\\x86_64-w64-mingw32","-isystem","D:\\Qt\\Tools\\mingw1120_64\\lib\\gcc\\x86_64-w64-mingw32\\11.2.0\\include\\c++\\backward","-isystem","D:\\Qt\\Tools\\QtCreator\\bin\\clang\\lib\\clang\\18\\include","-isystem","D:\\Qt\\Tools\\mingw1120_64\\x86_64-w64-mingw32\\include","-fmessage-length=0","-fdiagnostics-show-note-include-stack","-fretain-comments-from-system-headers","-fmacro-backtrace-limit=0","-ferror-limit=1000","-x","c++","D:\\GitTest\\Bejeweled4\\signup.cpp"],"directory":"D:/GitTest/Bejeweled4/build/Desktop_Qt_6_5_3_MinGW_64_bit-Debug/.qtc_clangd","file":"D:/GitTest/Bejeweled4/signup.cpp"},{"arguments":["clang","-Wno-documentation-unknown-command","-Wno-unknown-warning-option","-Wno-unknown-pragmas","-nostdinc","-nostdinc++","-g","-std=gnu++1z","-Wall","-Wextra","-Wextra","-fexceptions","-mthreads","-fsyntax-only","-m64","--target=x86_64-w64-mingw32","-DUNICODE","-D_UNICODE","-DWIN32","-DMINGW_HAS_SECURE_API","-DQT_QML_DEBUG","-DQT_WIDGETS_LIB","-DQT_MULTIMEDIA_LIB","-DQT_GUI_LIB","-DQT_NETWORK_LIB","-DQT_SQL_LIB","-DQT_CORE_LIB","-DQT_NEEDS_QMAIN","-DQ_CREATOR_RUN","-DQT_ANNOTATE_FUNCTION(x)=__attribute__((annotate(#x)))","-ID:\\Qt\\Tools\\QtCreator\\share\\qtcreator\\cplusplus\\wrappedMingwHeaders","-ID:\\Qt\\Tools\\QtCreator\\share\\qtcreator\\cplusplus\\wrappedQtHeaders","-ID:\\Qt\\Tools\\QtCreator\\share\\qtcreator\\cplusplus\\wrappedQtHeaders\\QtCore","-ID:\\GitTest\\Bejeweled4","-ID:\\Qt\\6.5.3\\mingw_64\\include","-ID:\\Qt\\6.5.3\\mingw_64\\include\\QtWidgets","-ID:\\Qt\\6.5.3\\mingw_64\\include\\QtMultimedia","-ID:\\Qt\\6.5.3\\mingw_64\\include\\QtGui","-ID:\\Qt\\6.5.3\\mingw_64\\include\\QtNetwork","-ID:\\Qt\\6.5.3\\mingw_64\\include\\QtSql","-ID:\\Qt\\6.5.3\\mingw_64\\include\\QtCore","-ID:\\GitTest\\Bejeweled4\\build\\Desktop_Qt_6_5_3_MinGW_64_bit-Debug\\debug","-ID:\\GitTest\\Bejeweled4\\build\\Desktop_Qt_6_5_3_MinGW_64_bit-Debug","-ID:\\Qt\\6.5.3\\mingw_64\\mkspecs\\win32-g++","-isystem","D:\\Qt\\Tools\\mingw1120_64\\lib\\gcc\\x86_64-w64-mingw32\\11.2.0\\include\\c++","-isystem","D:\\Qt\\Tools\\mingw1120_64\\lib\\gcc\\x86_64-w64-mingw32\\11.2.0\\include\\c++\\x86_64-w64-mingw32","-isystem","D:\\Qt\\Tools\\mingw1120_64\\lib\\gcc\\x86_64-w64-mingw32\\11.2.0\\include\\c++\\backward","-isystem","D:\\Qt\\Tools\\QtCreator\\bin\\clang\\lib\\clang\\18\\include","-isystem","D:\\Qt\\Tools\\mingw1120_64\\x86_64-w64-mingw32\\include","-fmessage-length=0","-fdiagnostics-show-note-include-stack","-fretain-comments-from-system-headers","-fmacro-backtrace-limit=0","-ferror-limit=1000","-x","c++","D:\\GitTest\\Bejeweled4\\stonelabel.cpp"],"directory":"D:/GitTest/Bejeweled4/build/Desktop_Qt_6_5_3_MinGW_64_bit-Debug/.qtc_clangd","file":"D:/GitTest/Bejeweled4/stonelabel.cpp"},{"arguments":["clang","-Wno-documentation-unknown-command","-Wno-unknown-warning-option","-Wno-unknown-pragmas","-nostdinc","-nostdinc++","-g","-std=gnu++1z","-Wall","-Wextra","-Wextra","-fexceptions","-mthreads","-fsyntax-only","-m64","--target=x86_64-w64-mingw32","-DUNICODE","-D_UNICODE","-DWIN32","-DMINGW_HAS_SECURE_API","-DQT_QML_DEBUG","-DQT_WIDGETS_LIB","-DQT_MULTIMEDIA_LIB","-DQT_GUI_LIB","-DQT_NETWORK_LIB","-DQT_SQL_LIB","-DQT_CORE_LIB","-DQT_NEEDS_QMAIN","-DQ_CREATOR_RUN","-DQT_ANNOTATE_FUNCTION(x)=__attribute__((annotate(#x)))","-ID:\\Qt\\Tools\\QtCreator\\share\\qtcreator\\cplusplus\\wrappedMingwHeaders","-ID:\\Qt\\Tools\\QtCreator\\share\\qtcreator\\cplusplus\\wrappedQtHeaders","-ID:\\Qt\\Tools\\QtCreator\\share\\qtcreator\\cplusplus\\wrappedQtHeaders\\QtCore","-ID:\\GitTest\\Bejeweled4","-ID:\\Qt\\6.5.3\\mingw_64\\include","-ID:\\Qt\\6.5.3\\mingw_64\\include\\QtWidgets","-ID:\\Qt\\6.5.3\\mingw_64\\include\\QtMultimedia","-ID:\\Qt\\6.5.3\\mingw_64\\include\\QtGui","-ID:\\Qt\\6.5.3\\mingw_64\\include\\QtNetwork","-ID:\\Qt\\6.5.3\\mingw_64\\include\\QtSql","-ID:\\Qt\\6.5.3\\mingw_64\\include\\QtCore","-ID:\\GitTest\\Bejeweled4\\build\\Desktop_Qt_6_5_3_MinGW_64_bit-Debug\\debug","-ID:\\GitTest\\Bejeweled4\\build\\Desktop_Qt_6_5_3_MinGW_64_bit-Debug","-ID:\\Qt\\6.5.3\\mingw_64\\mkspecs\\win32-g++","-isystem","D:\\Qt\\Tools\\mingw1120_64\\lib\\gcc\\x86_64-w64-mingw32\\11.2.0\\include\\c++","-isystem","D:\\Qt\\Tools\\mingw1120_64\\lib\\gcc\\x86_64-w64-mingw32\\11.2.0\\include\\c++\\x86_64-w64-mingw32","-isystem","D:\\Qt\\Tools\\mingw1120_64\\lib\\gcc\\x86_64-w64-mingw32\\11.2.0\\include\\c++\\backward","-isystem","D:\\Qt\\Tools\\QtCreator\\bin\\clang\\lib\\clang\\18\\include","-isystem","D:\\Qt\\Tools\\mingw1120_64\\x86_64-w64-mingw32\\include","-fmessage-length=0","-fdiagnostics-show-note-include-stack","-fretain-comments-from-system-headers","-fmacro-backtrace-limit=0","-ferror-limit=1000","-x","c++","D:\\GitTest\\Bejeweled4\\utils.cpp"],"directory":"D:/GitTest/Bejeweled4/build/Desktop_Qt_6_5_3_MinGW_64_bit-Debug/.qtc_clangd","file":"D:/GitTest/Bejeweled4/utils.cpp"},{"arguments":["clang","-Wno-documentation-unknown-command","-Wno-unknown-warning-option","-Wno-unknown-pragmas","-nostdinc","-nostdinc++","-g","-std=gnu++1z","-Wall","-Wextra","-Wextra","-fexceptions","-mthreads","-fsyntax-only","-m64","--target=x86_64-w64-mingw32","-DUNICODE","-D_UNICODE","-DWIN32","-DMINGW_HAS_SECURE_API","-DQT_QML_DEBUG","-DQT_WIDGETS_LIB","-DQT_MULTIMEDIA_LIB","-DQT_GUI_LIB","-DQT_NETWORK_LIB","-DQT_SQL_LIB","-DQT_CORE_LIB","-DQT_NEEDS_QMAIN","-DQ_CREATOR_RUN","-DQT_ANNOTATE_FUNCTION(x)=__attribute__((annotate(#x)))","-ID:\\Qt\\Tools\\QtCreator\\share\\qtcreator\\cplusplus\\wrappedMingwHeaders","-ID:\\Qt\\Tools\\QtCreator\\share\\qtcreator\\cplusplus\\wrappedQtHeaders","-ID:\\Qt\\Tools\\QtCreator\\share\\qtcreator\\cplusplus\\wrappedQtHeaders\\QtCore","-ID:\\GitTest\\Bejeweled4","-ID:\\Qt\\6.5.3\\mingw_64\\include","-ID:\\Qt\\6.5.3\\mingw_64\\include\\QtWidgets","-ID:\\Qt\\6.5.3\\mingw_64\\include\\QtMultimedia","-ID:\\Qt\\6.5.3\\mingw_64\\include\\QtGui","-ID:\\Qt\\6.5.3\\mingw_64\\include\\QtNetwork","-ID:\\Qt\\6.5.3\\mingw_64\\include\\QtSql","-ID:\\Qt\\6.5.3\\mingw_64\\include\\QtCore","-ID:\\GitTest\\Bejeweled4\\build\\Desktop_Qt_6_5_3_MinGW_64_bit-Debug\\debug","-ID:\\GitTest\\Bejeweled4\\build\\Desktop_Qt_6_5_3_MinGW_64_bit-Debug","-ID:\\Qt\\6.5.3\\mingw_64\\mkspecs\\win32-g++","-isystem","D:\\Qt\\Tools\\mingw1120_64\\lib\\gcc\\x86_64-w64-mingw32\\11.2.0\\include\\c++","-isystem","D:\\Qt\\Tools\\mingw1120_64\\lib\\gcc\\x86_64-w64-mingw32\\11.2.0\\include\\c++\\x86_64-w64-mingw32","-isystem","D:\\Qt\\Tools\\mingw1120_64\\lib\\gcc\\x86_64-w64-mingw32\\11.2.0\\include\\c++\\backward","-isystem","D:\\Qt\\Tools\\QtCreator\\bin\\clang\\lib\\clang\\18\\include","-isystem","D:\\Qt\\Tools\\mingw1120_64\\x86_64-w64-mingw32\\include","-fmessage-length=0","-fdiagnostics-show-note-include-stack","-fretain-comments-from-system-headers","-fmacro-backtrace-limit=0","-ferror-limit=1000","-x","c++-header","D:\\GitTest\\Bejeweled4\\Login.h"],"directory":"D:/GitTest/Bejeweled4/build/Desktop_Qt_6_5_3_MinGW_64_bit-Debug/.qtc_clangd","file":"D:/GitTest/Bejeweled4/Login.h"},{"arguments":["clang","-Wno-documentation-unknown-command","-Wno-unknown-warning-option","-Wno-unknown-pragmas","-nostdinc","-nostdinc++","-g","-std=gnu++1z","-Wall","-Wextra","-Wextra","-fexceptions","-mthreads","-fsyntax-only","-m64","--target=x86_64-w64-mingw32","-DUNICODE","-D_UNICODE","-DWIN32","-DMINGW_HAS_SECURE_API","-DQT_QML_DEBUG","-DQT_WIDGETS_LIB","-DQT_MULTIMEDIA_LIB","-DQT_GUI_LIB","-DQT_NETWORK_LIB","-DQT_SQL_LIB","-DQT_CORE_LIB","-DQT_NEEDS_QMAIN","-DQ_CREATOR_RUN","-DQT_ANNOTATE_FUNCTION(x)=__attribute__((annotate(#x)))","-ID:\\Qt\\Tools\\QtCreator\\share\\qtcreator\\cplusplus\\wrappedMingwHeaders","-ID:\\Qt\\Tools\\QtCreator\\share\\qtcreator\\cplusplus\\wrappedQtHeaders","-ID:\\Qt\\Tools\\QtCreator\\share\\qtcreator\\cplusplus\\wrappedQtHeaders\\QtCore","-ID:\\GitTest\\Bejeweled4","-ID:\\Qt\\6.5.3\\mingw_64\\include","-ID:\\Qt\\6.5.3\\mingw_64\\include\\QtWidgets","-ID:\\Qt\\6.5.3\\mingw_64\\include\\QtMultimedia","-ID:\\Qt\\6.5.3\\mingw_64\\include\\QtGui","-ID:\\Qt\\6.5.3\\mingw_64\\include\\QtNetwork","-ID:\\Qt\\6.5.3\\mingw_64\\include\\QtSql","-ID:\\Qt\\6.5.3\\mingw_64\\include\\QtCore","-ID:\\GitTest\\Bejeweled4\\build\\Desktop_Qt_6_5_3_MinGW_64_bit-Debug\\debug","-ID:\\GitTest\\Bejeweled4\\build\\Desktop_Qt_6_5_3_MinGW_64_bit-Debug","-ID:\\Qt\\6.5.3\\mingw_64\\mkspecs\\win32-g++","-isystem","D:\\Qt\\Tools\\mingw1120_64\\lib\\gcc\\x86_64-w64-mingw32\\11.2.0\\include\\c++","-isystem","D:\\Qt\\Tools\\mingw1120_64\\lib\\gcc\\x86_64-w64-mingw32\\11.2.0\\include\\c++\\x86_64-w64-mingw32","-isystem","D:\\Qt\\Tools\\mingw1120_64\\lib\\gcc\\x86_64-w64-mingw32\\11.2.0\\include\\c++\\backward","-isystem","D:\\Qt\\Tools\\QtCreator\\bin\\clang\\lib\\clang\\18\\include","-isystem","D:\\Qt\\Tools\\mingw1120_64\\x86_64-w64-mingw32\\include","-fmessage-length=0","-fdiagnostics-show-note-include-stack","-fretain-comments-from-system-headers","-fmacro-backtrace-limit=0","-ferror-limit=1000","-x","c++-header","D:\\GitTest\\Bejeweled4\\PixmapSlider.h"],"directory":"D:/GitTest/Bejeweled4/build/Desktop_Qt_6_5_3_MinGW_64_bit-Debug/.qtc_clangd","file":"D:/GitTest/Bejeweled4/PixmapSlider.h"},{"arguments":["clang","-Wno-documentation-unknown-command","-Wno-unknown-warning-option","-Wno-unknown-pragmas","-nostdinc","-nostdinc++","-g","-std=gnu++1z","-Wall","-Wextra","-Wextra","-fexceptions","-mthreads","-fsyntax-only","-m64","--target=x86_64-w64-mingw32","-DUNICODE","-D_UNICODE","-DWIN32","-DMINGW_HAS_SECURE_API","-DQT_QML_DEBUG","-DQT_WIDGETS_LIB","-DQT_MULTIMEDIA_LIB","-DQT_GUI_LIB","-DQT_NETWORK_LIB","-DQT_SQL_LIB","-DQT_CORE_LIB","-DQT_NEEDS_QMAIN","-DQ_CREATOR_RUN","-DQT_ANNOTATE_FUNCTION(x)=__attribute__((annotate(#x)))","-ID:\\Qt\\Tools\\QtCreator\\share\\qtcreator\\cplusplus\\wrappedMingwHeaders","-ID:\\Qt\\Tools\\QtCreator\\share\\qtcreator\\cplusplus\\wrappedQtHeaders","-ID:\\Qt\\Tools\\QtCreator\\share\\qtcreator\\cplusplus\\wrappedQtHeaders\\QtCore","-ID:\\GitTest\\Bejeweled4","-ID:\\Qt\\6.5.3\\mingw_64\\include","-ID:\\Qt\\6.5.3\\mingw_64\\include\\QtWidgets","-ID:\\Qt\\6.5.3\\mingw_64\\include\\QtMultimedia","-ID:\\Qt\\6.5.3\\mingw_64\\include\\QtGui","-ID:\\Qt\\6.5.3\\mingw_64\\include\\QtNetwork","-ID:\\Qt\\6.5.3\\mingw_64\\include\\QtSql","-ID:\\Qt\\6.5.3\\mingw_64\\include\\QtCore","-ID:\\GitTest\\Bejeweled4\\build\\Desktop_Qt_6_5_3_MinGW_64_bit-Debug\\debug","-ID:\\GitTest\\Bejeweled4\\build\\Desktop_Qt_6_5_3_MinGW_64_bit-Debug","-ID:\\Qt\\6.5.3\\mingw_64\\mkspecs\\win32-g++","-isystem","D:\\Qt\\Tools\\mingw1120_64\\lib\\gcc\\x86_64-w64-mingw32\\11.2.0\\include\\c++","-isystem","D:\\Qt\\Tools\\mingw1120_64\\lib\\gcc\\x86_64-w64-mingw32\\11.2.0\\include\\c++\\x86_64-w64-mingw32","-isystem","D:\\Qt\\Tools\\mingw1120_64\\lib\\gcc\\x86_64-w64-mingw32\\11.2.0\\include\\c++\\backward","-isystem","D:\\Qt\\Tools\\QtCreator\\bin\\clang\\lib\\clang\\18\\include","-isystem","D:\\Qt\\Tools\\mingw1120_64\\x86_64-w64-mingw32\\include","-fmessage-length=0","-fdiagnostics-show-note-include-stack","-fretain-comments-from-system-headers","-fmacro-backtrace-limit=0","-ferror-limit=1000","-x","c++-header","D:\\GitTest\\Bejeweled4\\client.h"],"directory":"D:/GitTest/Bejeweled4/build/Desktop_Qt_6_5_3_MinGW_64_bit-Debug/.qtc_clangd","file":"D:/GitTest/Bejeweled4/client.h"},{"arguments":["clang","-Wno-documentation-unknown-command","-Wno-unknown-warning-option","-Wno-unknown-pragmas","-nostdinc","-nostdinc++","-g","-std=gnu++1z","-Wall","-Wextra","-Wextra","-fexceptions","-mthreads","-fsyntax-only","-m64","--target=x86_64-w64-mingw32","-DUNICODE","-D_UNICODE","-DWIN32","-DMINGW_HAS_SECURE_API","-DQT_QML_DEBUG","-DQT_WIDGETS_LIB","-DQT_MULTIMEDIA_LIB","-DQT_GUI_LIB","-DQT_NETWORK_LIB","-DQT_SQL_LIB","-DQT_CORE_LIB","-DQT_NEEDS_QMAIN","-DQ_CREATOR_RUN","-DQT_ANNOTATE_FUNCTION(x)=__attribute__((annotate(#x)))","-ID:\\Qt\\Tools\\QtCreator\\share\\qtcreator\\cplusplus\\wrappedMingwHeaders","-ID:\\Qt\\Tools\\QtCreator\\share\\qtcreator\\cplusplus\\wrappedQtHeaders","-ID:\\Qt\\Tools\\QtCreator\\share\\qtcreator\\cplusplus\\wrappedQtHeaders\\QtCore","-ID:\\GitTest\\Bejeweled4","-ID:\\Qt\\6.5.3\\mingw_64\\include","-ID:\\Qt\\6.5.3\\mingw_64\\include\\QtWidgets","-ID:\\Qt\\6.5.3\\mingw_64\\include\\QtMultimedia","-ID:\\Qt\\6.5.3\\mingw_64\\include\\QtGui","-ID:\\Qt\\6.5.3\\mingw_64\\include\\QtNetwork","-ID:\\Qt\\6.5.3\\mingw_64\\include\\QtSql","-ID:\\Qt\\6.5.3\\mingw_64\\include\\QtCore","-ID:\\GitTest\\Bejeweled4\\build\\Desktop_Qt_6_5_3_MinGW_64_bit-Debug\\debug","-ID:\\GitTest\\Bejeweled4\\build\\Desktop_Qt_6_5_3_MinGW_64_bit-Debug","-ID:\\Qt\\6.5.3\\mingw_64\\mkspecs\\win32-g++","-isystem","D:\\Qt\\Tools\\mingw1120_64\\lib\\gcc\\x86_64-w64-mingw32\\11.2.0\\include\\c++","-isystem","D:\\Qt\\Tools\\mingw1120_64\\lib\\gcc\\x86_64-w64-mingw32\\11.2.0\\include\\c++\\x86_64-w64-mingw32","-isystem","D:\\Qt\\Tools\\mingw1120_64\\lib\\gcc\\x86_64-w64-mingw32\\11.2.0\\include\\c++\\backward","-isystem","D:\\Qt\\Tools\\QtCreator\\bin\\clang\\lib\\clang\\18\\include","-isystem","D:\\Qt\\Tools\\mingw1120_64\\x86_64-w64-mingw32\\include","-fmessage-length=0","-fdiagnostics-show-note-include-stack","-fretain-comments-from-system-headers","-fmacro-backtrace-limit=0","-ferror-limit=1000","-x","c++-header","D:\\GitTest\\Bejeweled4\\end.h"],"directory":"D:/GitTest/Bejeweled4/build/Desktop_Qt_6_5_3_MinGW_64_bit-Debug/.qtc_clangd","file":"D:/GitTest/Bejeweled4/end.h"},{"arguments":["clang","-Wno-documentation-unknown-command","-Wno-unknown-warning-option","-Wno-unknown-pragmas","-nostdinc","-nostdinc++","-g","-std=gnu++1z","-Wall","-Wextra","-Wextra","-fexceptions","-mthreads","-fsyntax-only","-m64","--target=x86_64-w64-mingw32","-DUNICODE","-D_UNICODE","-DWIN32","-DMINGW_HAS_SECURE_API","-DQT_QML_DEBUG","-DQT_WIDGETS_LIB","-DQT_MULTIMEDIA_LIB","-DQT_GUI_LIB","-DQT_NETWORK_LIB","-DQT_SQL_LIB","-DQT_CORE_LIB","-DQT_NEEDS_QMAIN","-DQ_CREATOR_RUN","-DQT_ANNOTATE_FUNCTION(x)=__attribute__((annotate(#x)))","-ID:\\Qt\\Tools\\QtCreator\\share\\qtcreator\\cplusplus\\wrappedMingwHeaders","-ID:\\Qt\\Tools\\QtCreator\\share\\qtcreator\\cplusplus\\wrappedQtHeaders","-ID:\\Qt\\Tools\\QtCreator\\share\\qtcreator\\cplusplus\\wrappedQtHeaders\\QtCore","-ID:\\GitTest\\Bejeweled4","-ID:\\Qt\\6.5.3\\mingw_64\\include","-ID:\\Qt\\6.5.3\\mingw_64\\include\\QtWidgets","-ID:\\Qt\\6.5.3\\mingw_64\\include\\QtMultimedia","-ID:\\Qt\\6.5.3\\mingw_64\\include\\QtGui","-ID:\\Qt\\6.5.3\\mingw_64\\include\\QtNetwork","-ID:\\Qt\\6.5.3\\mingw_64\\include\\QtSql","-ID:\\Qt\\6.5.3\\mingw_64\\include\\QtCore","-ID:\\GitTest\\Bejeweled4\\build\\Desktop_Qt_6_5_3_MinGW_64_bit-Debug\\debug","-ID:\\GitTest\\Bejeweled4\\build\\Desktop_Qt_6_5_3_MinGW_64_bit-Debug","-ID:\\Qt\\6.5.3\\mingw_64\\mkspecs\\win32-g++","-isystem","D:\\Qt\\Tools\\mingw1120_64\\lib\\gcc\\x86_64-w64-mingw32\\11.2.0\\include\\c++","-isystem","D:\\Qt\\Tools\\mingw1120_64\\lib\\gcc\\x86_64-w64-mingw32\\11.2.0\\include\\c++\\x86_64-w64-mingw32","-isystem","D:\\Qt\\Tools\\mingw1120_64\\lib\\gcc\\x86_64-w64-mingw32\\11.2.0\\include\\c++\\backward","-isystem","D:\\Qt\\Tools\\QtCreator\\bin\\clang\\lib\\clang\\18\\include","-isystem","D:\\Qt\\Tools\\mingw1120_64\\x86_64-w64-mingw32\\include","-fmessage-length=0","-fdiagnostics-show-note-include-stack","-fretain-comments-from-system-headers","-fmacro-backtrace-limit=0","-ferror-limit=1000","-x","c++-header","D:\\GitTest\\Bejeweled4\\game.h"],"directory":"D:/GitTest/Bejeweled4/build/Desktop_Qt_6_5_3_MinGW_64_bit-Debug/.qtc_clangd","file":"D:/GitTest/Bejeweled4/game.h"},{"arguments":["clang","-Wno-documentation-unknown-command","-Wno-unknown-warning-option","-Wno-unknown-pragmas","-nostdinc","-nostdinc++","-g","-std=gnu++1z","-Wall","-Wextra","-Wextra","-fexceptions","-mthreads","-fsyntax-only","-m64","--target=x86_64-w64-mingw32","-DUNICODE","-D_UNICODE","-DWIN32","-DMINGW_HAS_SECURE_API","-DQT_QML_DEBUG","-DQT_WIDGETS_LIB","-DQT_MULTIMEDIA_LIB","-DQT_GUI_LIB","-DQT_NETWORK_LIB","-DQT_SQL_LIB","-DQT_CORE_LIB","-DQT_NEEDS_QMAIN","-DQ_CREATOR_RUN","-DQT_ANNOTATE_FUNCTION(x)=__attribute__((annotate(#x)))","-ID:\\Qt\\Tools\\QtCreator\\share\\qtcreator\\cplusplus\\wrappedMingwHeaders","-ID:\\Qt\\Tools\\QtCreator\\share\\qtcreator\\cplusplus\\wrappedQtHeaders","-ID:\\Qt\\Tools\\QtCreator\\share\\qtcreator\\cplusplus\\wrappedQtHeaders\\QtCore","-ID:\\GitTest\\Bejeweled4","-ID:\\Qt\\6.5.3\\mingw_64\\include","-ID:\\Qt\\6.5.3\\mingw_64\\include\\QtWidgets","-ID:\\Qt\\6.5.3\\mingw_64\\include\\QtMultimedia","-ID:\\Qt\\6.5.3\\mingw_64\\include\\QtGui","-ID:\\Qt\\6.5.3\\mingw_64\\include\\QtNetwork","-ID:\\Qt\\6.5.3\\mingw_64\\include\\QtSql","-ID:\\Qt\\6.5.3\\mingw_64\\include\\QtCore","-ID:\\GitTest\\Bejeweled4\\build\\Desktop_Qt_6_5_3_MinGW_64_bit-Debug\\debug","-ID:\\GitTest\\Bejeweled4\\build\\Desktop_Qt_6_5_3_MinGW_64_bit-Debug","-ID:\\Qt\\6.5.3\\mingw_64\\mkspecs\\win32-g++","-isystem","D:\\Qt\\Tools\\mingw1120_64\\lib\\gcc\\x86_64-w64-mingw32\\11.2.0\\include\\c++","-isystem","D:\\Qt\\Tools\\mingw1120_64\\lib\\gcc\\x86_64-w64-mingw32\\11.2.0\\include\\c++\\x86_64-w64-mingw32","-isystem","D:\\Qt\\Tools\\mingw1120_64\\lib\\gcc\\x86_64-w64-mingw32\\11.2.0\\include\\c++\\backward","-isystem","D:\\Qt\\Tools\\QtCreator\\bin\\clang\\lib\\clang\\18\\include","-isystem","D:\\Qt\\Tools\\mingw1120_64\\x86_64-w64-mingw32\\include","-fmessage-length=0","-fdiagnostics-show-note-include-stack","-fretain-comments-from-system-headers","-fmacro-backtrace-limit=0","-ferror-limit=1000","-x","c++-header","D:\\GitTest\\Bejeweled4\\gametimer.h"],"directory":"D:/GitTest/Bejeweled4/build/Desktop_Qt_6_5_3_MinGW_64_bit-Debug/.qtc_clangd","file":"D:/GitTest/Bejeweled4/gametimer.h"},{"arguments":["clang","-Wno-documentation-unknown-command","-Wno-unknown-warning-option","-Wno-unknown-pragmas","-nostdinc","-nostdinc++","-g","-std=gnu++1z","-Wall","-Wextra","-Wextra","-fexceptions","-mthreads","-fsyntax-only","-m64","--target=x86_64-w64-mingw32","-DUNICODE","-D_UNICODE","-DWIN32","-DMINGW_HAS_SECURE_API","-DQT_QML_DEBUG","-DQT_WIDGETS_LIB","-DQT_MULTIMEDIA_LIB","-DQT_GUI_LIB","-DQT_NETWORK_LIB","-DQT_SQL_LIB","-DQT_CORE_LIB","-DQT_NEEDS_QMAIN","-DQ_CREATOR_RUN","-DQT_ANNOTATE_FUNCTION(x)=__attribute__((annotate(#x)))","-ID:\\Qt\\Tools\\QtCreator\\share\\qtcreator\\cplusplus\\wrappedMingwHeaders","-ID:\\Qt\\Tools\\QtCreator\\share\\qtcreator\\cplusplus\\wrappedQtHeaders","-ID:\\Qt\\Tools\\QtCreator\\share\\qtcreator\\cplusplus\\wrappedQtHeaders\\QtCore","-ID:\\GitTest\\Bejeweled4","-ID:\\Qt\\6.5.3\\mingw_64\\include","-ID:\\Qt\\6.5.3\\mingw_64\\include\\QtWidgets","-ID:\\Qt\\6.5.3\\mingw_64\\include\\QtMultimedia","-ID:\\Qt\\6.5.3\\mingw_64\\include\\QtGui","-ID:\\Qt\\6.5.3\\mingw_64\\include\\QtNetwork","-ID:\\Qt\\6.5.3\\mingw_64\\include\\QtSql","-ID:\\Qt\\6.5.3\\mingw_64\\include\\QtCore","-ID:\\GitTest\\Bejeweled4\\build\\Desktop_Qt_6_5_3_MinGW_64_bit-Debug\\debug","-ID:\\GitTest\\Bejeweled4\\build\\Desktop_Qt_6_5_3_MinGW_64_bit-Debug","-ID:\\Qt\\6.5.3\\mingw_64\\mkspecs\\win32-g++","-isystem","D:\\Qt\\Tools\\mingw1120_64\\lib\\gcc\\x86_64-w64-mingw32\\11.2.0\\include\\c++","-isystem","D:\\Qt\\Tools\\mingw1120_64\\lib\\gcc\\x86_64-w64-mingw32\\11.2.0\\include\\c++\\x86_64-w64-mingw32","-isystem","D:\\Qt\\Tools\\mingw1120_64\\lib\\gcc\\x86_64-w64-mingw32\\11.2.0\\include\\c++\\backward","-isystem","D:\\Qt\\Tools\\QtCreator\\bin\\clang\\lib\\clang\\18\\include","-isystem","D:\\Qt\\Tools\\mingw1120_64\\x86_64-w64-mingw32\\include","-fmessage-length=0","-fdiagnostics-show-note-include-stack","-fretain-comments-from-system-headers","-fmacro-backtrace-limit=0","-ferror-limit=1000","-x","c++-header","D:\\GitTest\\Bejeweled4\\globalvalue.h"],"directory":"D:/GitTest/Bejeweled4/build/Desktop_Qt_6_5_3_MinGW_64_bit-Debug/.qtc_clangd","file":"D:/GitTest/Bejeweled4/globalvalue.h"},{"arguments":["clang","-Wno-documentation-unknown-command","-Wno-unknown-warning-option","-Wno-unknown-pragmas","-nostdinc","-nostdinc++","-g","-std=gnu++1z","-Wall","-Wextra","-Wextra","-fexceptions","-mthreads","-fsyntax-only","-m64","--target=x86_64-w64-mingw32","-DUNICODE","-D_UNICODE","-DWIN32","-DMINGW_HAS_SECURE_API","-DQT_QML_DEBUG","-DQT_WIDGETS_LIB","-DQT_MULTIMEDIA_LIB","-DQT_GUI_LIB","-DQT_NETWORK_LIB","-DQT_SQL_LIB","-DQT_CORE_LIB","-DQT_NEEDS_QMAIN","-DQ_CREATOR_RUN","-DQT_ANNOTATE_FUNCTION(x)=__attribute__((annotate(#x)))","-ID:\\Qt\\Tools\\QtCreator\\share\\qtcreator\\cplusplus\\wrappedMingwHeaders","-ID:\\Qt\\Tools\\QtCreator\\share\\qtcreator\\cplusplus\\wrappedQtHeaders","-ID:\\Qt\\Tools\\QtCreator\\share\\qtcreator\\cplusplus\\wrappedQtHeaders\\QtCore","-ID:\\GitTest\\Bejeweled4","-ID:\\Qt\\6.5.3\\mingw_64\\include","-ID:\\Qt\\6.5.3\\mingw_64\\include\\QtWidgets","-ID:\\Qt\\6.5.3\\mingw_64\\include\\QtMultimedia","-ID:\\Qt\\6.5.3\\mingw_64\\include\\QtGui","-ID:\\Qt\\6.5.3\\mingw_64\\include\\QtNetwork","-ID:\\Qt\\6.5.3\\mingw_64\\include\\QtSql","-ID:\\Qt\\6.5.3\\mingw_64\\include\\QtCore","-ID:\\GitTest\\Bejeweled4\\build\\Desktop_Qt_6_5_3_MinGW_64_bit-Debug\\debug","-ID:\\GitTest\\Bejeweled4\\build\\Desktop_Qt_6_5_3_MinGW_64_bit-Debug","-ID:\\Qt\\6.5.3\\mingw_64\\mkspecs\\win32-g++","-isystem","D:\\Qt\\Tools\\mingw1120_64\\lib\\gcc\\x86_64-w64-mingw32\\11.2.0\\include\\c++","-isystem","D:\\Qt\\Tools\\mingw1120_64\\lib\\gcc\\x86_64-w64-mingw32\\11.2.0\\include\\c++\\x86_64-w64-mingw32","-isystem","D:\\Qt\\Tools\\mingw1120_64\\lib\\gcc\\x86_64-w64-mingw32\\11.2.0\\include\\c++\\backward","-isystem","D:\\Qt\\Tools\\QtCreator\\bin\\clang\\lib\\clang\\18\\include","-isystem","D:\\Qt\\Tools\\mingw1120_64\\x86_64-w64-mingw32\\include","-fmessage-length=0","-fdiagnostics-show-note-include-stack","-fretain-comments-from-system-headers","-fmacro-backtrace-limit=0","-ferror-limit=1000","-x","c++-header","D:\\GitTest\\Bejeweled4\\hoverbutton.h"],"directory":"D:/GitTest/Bejeweled4/build/Desktop_Qt_6_5_3_MinGW_64_bit-Debug/.qtc_clangd","file":"D:/GitTest/Bejeweled4/hoverbutton.h"},{"arguments":["clang","-Wno-documentation-unknown-command","-Wno-unknown-warning-option","-Wno-unknown-pragmas","-nostdinc","-nostdinc++","-g","-std=gnu++1z","-Wall","-Wextra","-Wextra","-fexceptions","-mthreads","-fsyntax-only","-m64","--target=x86_64-w64-mingw32","-DUNICODE","-D_UNICODE","-DWIN32","-DMINGW_HAS_SECURE_API","-DQT_QML_DEBUG","-DQT_WIDGETS_LIB","-DQT_MULTIMEDIA_LIB","-DQT_GUI_LIB","-DQT_NETWORK_LIB","-DQT_SQL_LIB","-DQT_CORE_LIB","-DQT_NEEDS_QMAIN","-DQ_CREATOR_RUN","-DQT_ANNOTATE_FUNCTION(x)=__attribute__((annotate(#x)))","-ID:\\Qt\\Tools\\QtCreator\\share\\qtcreator\\cplusplus\\wrappedMingwHeaders","-ID:\\Qt\\Tools\\QtCreator\\share\\qtcreator\\cplusplus\\wrappedQtHeaders","-ID:\\Qt\\Tools\\QtCreator\\share\\qtcreator\\cplusplus\\wrappedQtHeaders\\QtCore","-ID:\\GitTest\\Bejeweled4","-ID:\\Qt\\6.5.3\\mingw_64\\include","-ID:\\Qt\\6.5.3\\mingw_64\\include\\QtWidgets","-ID:\\Qt\\6.5.3\\mingw_64\\include\\QtMultimedia","-ID:\\Qt\\6.5.3\\mingw_64\\include\\QtGui","-ID:\\Qt\\6.5.3\\mingw_64\\include\\QtNetwork","-ID:\\Qt\\6.5.3\\mingw_64\\include\\QtSql","-ID:\\Qt\\6.5.3\\mingw_64\\include\\QtCore","-ID:\\GitTest\\Bejeweled4\\build\\Desktop_Qt_6_5_3_MinGW_64_bit-Debug\\debug","-ID:\\GitTest\\Bejeweled4\\build\\Desktop_Qt_6_5_3_MinGW_64_bit-Debug","-ID:\\Qt\\6.5.3\\mingw_64\\mkspecs\\win32-g++","-isystem","D:\\Qt\\Tools\\mingw1120_64\\lib\\gcc\\x86_64-w64-mingw32\\11.2.0\\include\\c++","-isystem","D:\\Qt\\Tools\\mingw1120_64\\lib\\gcc\\x86_64-w64-mingw32\\11.2.0\\include\\c++\\x86_64-w64-mingw32","-isystem","D:\\Qt\\Tools\\mingw1120_64\\lib\\gcc\\x86_64-w64-mingw32\\11.2.0\\include\\c++\\backward","-isystem","D:\\Qt\\Tools\\QtCreator\\bin\\clang\\lib\\clang\\18\\include","-isystem","D:\\Qt\\Tools\\mingw1120_64\\x86_64-w64-mingw32\\include","-fmessage-length=0","-fdiagnostics-show-note-include-stack","-fretain-comments-from-system-headers","-fmacro-backtrace-limit=0","-ferror-limit=1000","-x","c++-header","D:\\GitTest\\Bejeweled4\\mainwindow.h"],"directory":"D:/GitTest/Bejeweled4/build/Desktop_Qt_6_5_3_MinGW_64_bit-Debug/.qtc_clangd","file":"D:/GitTest/Bejeweled4/mainwindow.h"},{"arguments":["clang","-Wno-documentation-unknown-command","-Wno-unknown-warning-option","-Wno-unknown-pragmas","-nostdinc","-nostdinc++","-g","-std=gnu++1z","-Wall","-Wextra","-Wextra","-fexceptions","-mthreads","-fsyntax-only","-m64","--target=x86_64-w64-mingw32","-DUNICODE","-D_UNICODE","-DWIN32","-DMINGW_HAS_SECURE_API","-DQT_QML_DEBUG","-DQT_WIDGETS_LIB","-DQT_MULTIMEDIA_LIB","-DQT_GUI_LIB","-DQT_NETWORK_LIB","-DQT_SQL_LIB","-DQT_CORE_LIB","-DQT_NEEDS_QMAIN","-DQ_CREATOR_RUN","-DQT_ANNOTATE_FUNCTION(x)=__attribute__((annotate(#x)))","-ID:\\Qt\\Tools\\QtCreator\\share\\qtcreator\\cplusplus\\wrappedMingwHeaders","-ID:\\Qt\\Tools\\QtCreator\\share\\qtcreator\\cplusplus\\wrappedQtHeaders","-ID:\\Qt\\Tools\\QtCreator\\share\\qtcreator\\cplusplus\\wrappedQtHeaders\\QtCore","-ID:\\GitTest\\Bejeweled4","-ID:\\Qt\\6.5.3\\mingw_64\\include","-ID:\\Qt\\6.5.3\\mingw_64\\include\\QtWidgets","-ID:\\Qt\\6.5.3\\mingw_64\\include\\QtMultimedia","-ID:\\Qt\\6.5.3\\mingw_64\\include\\QtGui","-ID:\\Qt\\6.5.3\\mingw_64\\include\\QtNetwork","-ID:\\Qt\\6.5.3\\mingw_64\\include\\QtSql","-ID:\\Qt\\6.5.3\\mingw_64\\include\\QtCore","-ID:\\GitTest\\Bejeweled4\\build\\Desktop_Qt_6_5_3_MinGW_64_bit-Debug\\debug","-ID:\\GitTest\\Bejeweled4\\build\\Desktop_Qt_6_5_3_MinGW_64_bit-Debug","-ID:\\Qt\\6.5.3\\mingw_64\\mkspecs\\win32-g++","-isystem","D:\\Qt\\Tools\\mingw1120_64\\lib\\gcc\\x86_64-w64-mingw32\\11.2.0\\include\\c++","-isystem","D:\\Qt\\Tools\\mingw1120_64\\lib\\gcc\\x86_64-w64-mingw32\\11.2.0\\include\\c++\\x86_64-w64-mingw32","-isystem","D:\\Qt\\Tools\\mingw1120_64\\lib\\gcc\\x86_64-w64-mingw32\\11.2.0\\include\\c++\\backward","-isystem","D:\\Qt\\Tools\\QtCreator\\bin\\clang\\lib\\clang\\18\\include","-isystem","D:\\Qt\\Tools\\mingw1120_64\\x86_64-w64-mingw32\\include","-fmessage-length=0","-fdiagnostics-show-note-include-stack","-fretain-comments-from-system-headers","-fmacro-backtrace-limit=0","-ferror-limit=1000","-x","c++-header","D:\\GitTest\\Bejeweled4\\rankdialog.h"],"directory":"D:/GitTest/Bejeweled4/build/Desktop_Qt_6_5_3_MinGW_64_bit-Debug/.qtc_clangd","file":"D:/GitTest/Bejeweled4/rankdialog.h"},{"arguments":["clang","-Wno-documentation-unknown-command","-Wno-unknown-warning-option","-Wno-unknown-pragmas","-nostdinc","-nostdinc++","-g","-std=gnu++1z","-Wall","-Wextra","-Wextra","-fexceptions","-mthreads","-fsyntax-only","-m64","--target=x86_64-w64-mingw32","-DUNICODE","-D_UNICODE","-DWIN32","-DMINGW_HAS_SECURE_API","-DQT_QML_DEBUG","-DQT_WIDGETS_LIB","-DQT_MULTIMEDIA_LIB","-DQT_GUI_LIB","-DQT_NETWORK_LIB","-DQT_SQL_LIB","-DQT_CORE_LIB","-DQT_NEEDS_QMAIN","-DQ_CREATOR_RUN","-DQT_ANNOTATE_FUNCTION(x)=__attribute__((annotate(#x)))","-ID:\\Qt\\Tools\\QtCreator\\share\\qtcreator\\cplusplus\\wrappedMingwHeaders","-ID:\\Qt\\Tools\\QtCreator\\share\\qtcreator\\cplusplus\\wrappedQtHeaders","-ID:\\Qt\\Tools\\QtCreator\\share\\qtcreator\\cplusplus\\wrappedQtHeaders\\QtCore","-ID:\\GitTest\\Bejeweled4","-ID:\\Qt\\6.5.3\\mingw_64\\include","-ID:\\Qt\\6.5.3\\mingw_64\\include\\QtWidgets","-ID:\\Qt\\6.5.3\\mingw_64\\include\\QtMultimedia","-ID:\\Qt\\6.5.3\\mingw_64\\include\\QtGui","-ID:\\Qt\\6.5.3\\mingw_64\\include\\QtNetwork","-ID:\\Qt\\6.5.3\\mingw_64\\include\\QtSql","-ID:\\Qt\\6.5.3\\mingw_64\\include\\QtCore","-ID:\\GitTest\\Bejeweled4\\build\\Desktop_Qt_6_5_3_MinGW_64_bit-Debug\\debug","-ID:\\GitTest\\Bejeweled4\\build\\Desktop_Qt_6_5_3_MinGW_64_bit-Debug","-ID:\\Qt\\6.5.3\\mingw_64\\mkspecs\\win32-g++","-isystem","D:\\Qt\\Tools\\mingw1120_64\\lib\\gcc\\x86_64-w64-mingw32\\11.2.0\\include\\c++","-isystem","D:\\Qt\\Tools\\mingw1120_64\\lib\\gcc\\x86_64-w64-mingw32\\11.2.0\\include\\c++\\x86_64-w64-mingw32","-isystem","D:\\Qt\\Tools\\mingw1120_64\\lib\\gcc\\x86_64-w64-mingw32\\11.2.0\\include\\c++\\backward","-isystem","D:\\Qt\\Tools\\QtCreator\\bin\\clang\\lib\\clang\\18\\include","-isystem","D:\\Qt\\Tools\\mingw1120_64\\x86_64-w64-mingw32\\include","-fmessage-length=0","-fdiagnostics-show-note-include-stack","-fretain-comments-from-system-headers","-fmacro-backtrace-limit=0","-ferror-limit=1000","-x","c++-header","D:\\GitTest\\Bejeweled4\\settingwidget.h"],"directory":"D:/GitTest/Bejeweled4/build/Desktop_Qt_6_5_3_MinGW_64_bit-Debug/.qtc_clangd","file":"D:/GitTest/Bejeweled4/settingwidget.h"},{"arguments":["clang","-Wno-documentation-unknown-command","-Wno-unknown-warning-option","-Wno-unknown-pragmas","-nostdinc","-nostdinc++","-g","-std=gnu++1z","-Wall","-Wextra","-Wextra","-fexceptions","-mthreads","-fsyntax-only","-m64","--target=x86_64-w64-mingw32","-DUNICODE","-D_UNICODE","-DWIN32","-DMINGW_HAS_SECURE_API","-DQT_QML_DEBUG","-DQT_WIDGETS_LIB","-DQT_MULTIMEDIA_LIB","-DQT_GUI_LIB","-DQT_NETWORK_LIB","-DQT_SQL_LIB","-DQT_CORE_LIB","-DQT_NEEDS_QMAIN","-DQ_CREATOR_RUN","-DQT_ANNOTATE_FUNCTION(x)=__attribute__((annotate(#x)))","-ID:\\Qt\\Tools\\QtCreator\\share\\qtcreator\\cplusplus\\wrappedMingwHeaders","-ID:\\Qt\\Tools\\QtCreator\\share\\qtcreator\\cplusplus\\wrappedQtHeaders","-ID:\\Qt\\Tools\\QtCreator\\share\\qtcreator\\cplusplus\\wrappedQtHeaders\\QtCore","-ID:\\GitTest\\Bejeweled4","-ID:\\Qt\\6.5.3\\mingw_64\\include","-ID:\\Qt\\6.5.3\\mingw_64\\include\\QtWidgets","-ID:\\Qt\\6.5.3\\mingw_64\\include\\QtMultimedia","-ID:\\Qt\\6.5.3\\mingw_64\\include\\QtGui","-ID:\\Qt\\6.5.3\\mingw_64\\include\\QtNetwork","-ID:\\Qt\\6.5.3\\mingw_64\\include\\QtSql","-ID:\\Qt\\6.5.3\\mingw_64\\include\\QtCore","-ID:\\GitTest\\Bejeweled4\\build\\Desktop_Qt_6_5_3_MinGW_64_bit-Debug\\debug","-ID:\\GitTest\\Bejeweled4\\build\\Desktop_Qt_6_5_3_MinGW_64_bit-Debug","-ID:\\Qt\\6.5.3\\mingw_64\\mkspecs\\win32-g++","-isystem","D:\\Qt\\Tools\\mingw1120_64\\lib\\gcc\\x86_64-w64-mingw32\\11.2.0\\include\\c++","-isystem","D:\\Qt\\Tools\\mingw1120_64\\lib\\gcc\\x86_64-w64-mingw32\\11.2.0\\include\\c++\\x86_64-w64-mingw32","-isystem","D:\\Qt\\Tools\\mingw1120_64\\lib\\gcc\\x86_64-w64-mingw32\\11.2.0\\include\\c++\\backward","-isystem","D:\\Qt\\Tools\\QtCreator\\bin\\clang\\lib\\clang\\18\\include","-isystem","D:\\Qt\\Tools\\mingw1120_64\\x86_64-w64-mingw32\\include","-fmessage-length=0","-fdiagnostics-show-note-include-stack","-fretain-comments-from-system-headers","-fmacro-backtrace-limit=0","-ferror-limit=1000","-x","c++-header","D:\\GitTest\\Bejeweled4\\pause.h"],"directory":"D:/GitTest/Bejeweled4/build/Desktop_Qt_6_5_3_MinGW_64_bit-Debug/.qtc_clangd","file":"D:/GitTest/Bejeweled4/pause.h"},{"arguments":["clang","-Wno-documentation-unknown-command","-Wno-unknown-warning-option","-Wno-unknown-pragmas","-nostdinc","-nostdinc++","-g","-std=gnu++1z","-Wall","-Wextra","-Wextra","-fexceptions","-mthreads","-fsyntax-only","-m64","--target=x86_64-w64-mingw32","-DUNICODE","-D_UNICODE","-DWIN32","-DMINGW_HAS_SECURE_API","-DQT_QML_DEBUG","-DQT_WIDGETS_LIB","-DQT_MULTIMEDIA_LIB","-DQT_GUI_LIB","-DQT_NETWORK_LIB","-DQT_SQL_LIB","-DQT_CORE_LIB","-DQT_NEEDS_QMAIN","-DQ_CREATOR_RUN","-DQT_ANNOTATE_FUNCTION(x)=__attribute__((annotate(#x)))","-ID:\\Qt\\Tools\\QtCreator\\share\\qtcreator\\cplusplus\\wrappedMingwHeaders","-ID:\\Qt\\Tools\\QtCreator\\share\\qtcreator\\cplusplus\\wrappedQtHeaders","-ID:\\Qt\\Tools\\QtCreator\\share\\qtcreator\\cplusplus\\wrappedQtHeaders\\QtCore","-ID:\\GitTest\\Bejeweled4","-ID:\\Qt\\6.5.3\\mingw_64\\include","-ID:\\Qt\\6.5.3\\mingw_64\\include\\QtWidgets","-ID:\\Qt\\6.5.3\\mingw_64\\include\\QtMultimedia","-ID:\\Qt\\6.5.3\\mingw_64\\include\\QtGui","-ID:\\Qt\\6.5.3\\mingw_64\\include\\QtNetwork","-ID:\\Qt\\6.5.3\\mingw_64\\include\\QtSql","-ID:\\Qt\\6.5.3\\mingw_64\\include\\QtCore","-ID:\\GitTest\\Bejeweled4\\build\\Desktop_Qt_6_5_3_MinGW_64_bit-Debug\\debug","-ID:\\GitTest\\Bejeweled4\\build\\Desktop_Qt_6_5_3_MinGW_64_bit-Debug","-ID:\\Qt\\6.5.3\\mingw_64\\mkspecs\\win32-g++","-isystem","D:\\Qt\\Tools\\mingw1120_64\\lib\\gcc\\x86_64-w64-mingw32\\11.2.0\\include\\c++","-isystem","D:\\Qt\\Tools\\mingw1120_64\\lib\\gcc\\x86_64-w64-mingw32\\11.2.0\\include\\c++\\x86_64-w64-mingw32","-isystem","D:\\Qt\\Tools\\mingw1120_64\\lib\\gcc\\x86_64-w64-mingw32\\11.2.0\\include\\c++\\backward","-isystem","D:\\Qt\\Tools\\QtCreator\\bin\\clang\\lib\\clang\\18\\include","-isystem","D:\\Qt\\Tools\\mingw1120_64\\x86_64-w64-mingw32\\include","-fmessage-length=0","-fdiagnostics-show-note-include-stack","-fretain-comments-from-system-headers","-fmacro-backtrace-limit=0","-ferror-limit=1000","-x","c++-header","D:\\GitTest\\Bejeweled4\\shopwidget.h"],"directory":"D:/GitTest/Bejeweled4/build/Desktop_Qt_6_5_3_MinGW_64_bit-Debug/.qtc_clangd","file":"D:/GitTest/Bejeweled4/shopwidget.h"},{"arguments":["clang","-Wno-documentation-unknown-command","-Wno-unknown-warning-option","-Wno-unknown-pragmas","-nostdinc","-nostdinc++","-g","-std=gnu++1z","-Wall","-Wextra","-Wextra","-fexceptions","-mthreads","-fsyntax-only","-m64","--target=x86_64-w64-mingw32","-DUNICODE","-D_UNICODE","-DWIN32","-DMINGW_HAS_SECURE_API","-DQT_QML_DEBUG","-DQT_WIDGETS_LIB","-DQT_MULTIMEDIA_LIB","-DQT_GUI_LIB","-DQT_NETWORK_LIB","-DQT_SQL_LIB","-DQT_CORE_LIB","-DQT_NEEDS_QMAIN","-DQ_CREATOR_RUN","-DQT_ANNOTATE_FUNCTION(x)=__attribute__((annotate(#x)))","-ID:\\Qt\\Tools\\QtCreator\\share\\qtcreator\\cplusplus\\wrappedMingwHeaders","-ID:\\Qt\\Tools\\QtCreator\\share\\qtcreator\\cplusplus\\wrappedQtHeaders","-ID:\\Qt\\Tools\\QtCreator\\share\\qtcreator\\cplusplus\\wrappedQtHeaders\\QtCore","-ID:\\GitTest\\Bejeweled4","-ID:\\Qt\\6.5.3\\mingw_64\\include","-ID:\\Qt\\6.5.3\\mingw_64\\include\\QtWidgets","-ID:\\Qt\\6.5.3\\mingw_64\\include\\QtMultimedia","-ID:\\Qt\\6.5.3\\mingw_64\\include\\QtGui","-ID:\\Qt\\6.5.3\\mingw_64\\include\\QtNetwork","-ID:\\Qt\\6.5.3\\mingw_64\\include\\QtSql","-ID:\\Qt\\6.5.3\\mingw_64\\include\\QtCore","-ID:\\GitTest\\Bejeweled4\\build\\Desktop_Qt_6_5_3_MinGW_64_bit-Debug\\debug","-ID:\\GitTest\\Bejeweled4\\build\\Desktop_Qt_6_5_3_MinGW_64_bit-Debug","-ID:\\Qt\\6.5.3\\mingw_64\\mkspecs\\win32-g++","-isystem","D:\\Qt\\Tools\\mingw1120_64\\lib\\gcc\\x86_64-w64-mingw32\\11.2.0\\include\\c++","-isystem","D:\\Qt\\Tools\\mingw1120_64\\lib\\gcc\\x86_64-w64-mingw32\\11.2.0\\include\\c++\\x86_64-w64-mingw32","-isystem","D:\\Qt\\Tools\\mingw1120_64\\lib\\gcc\\x86_64-w64-mingw32\\11.2.0\\include\\c++\\backward","-isystem","D:\\Qt\\Tools\\QtCreator\\bin\\clang\\lib\\clang\\18\\include","-isystem","D:\\Qt\\Tools\\mingw1120_64\\x86_64-w64-mingw32\\include","-fmessage-length=0","-fdiagnostics-show-note-include-stack","-fretain-comments-from-system-headers","-fmacro-backtrace-limit=0","-ferror-limit=1000","-x","c++-header","D:\\GitTest\\Bejeweled4\\signup.h"],"directory":"D:/GitTest/Bejeweled4/build/Desktop_Qt_6_5_3_MinGW_64_bit-Debug/.qtc_clangd","file":"D:/GitTest/Bejeweled4/signup.h"},{"arguments":["clang","-Wno-documentation-unknown-command","-Wno-unknown-warning-option","-Wno-unknown-pragmas","-nostdinc","-nostdinc++","-g","-std=gnu++1z","-Wall","-Wextra","-Wextra","-fexceptions","-mthreads","-fsyntax-only","-m64","--target=x86_64-w64-mingw32","-DUNICODE","-D_UNICODE","-DWIN32","-DMINGW_HAS_SECURE_API","-DQT_QML_DEBUG","-DQT_WIDGETS_LIB","-DQT_MULTIMEDIA_LIB","-DQT_GUI_LIB","-DQT_NETWORK_LIB","-DQT_SQL_LIB","-DQT_CORE_LIB","-DQT_NEEDS_QMAIN","-DQ_CREATOR_RUN","-DQT_ANNOTATE_FUNCTION(x)=__attribute__((annotate(#x)))","-ID:\\Qt\\Tools\\QtCreator\\share\\qtcreator\\cplusplus\\wrappedMingwHeaders","-ID:\\Qt\\Tools\\QtCreator\\share\\qtcreator\\cplusplus\\wrappedQtHeaders","-ID:\\Qt\\Tools\\QtCreator\\share\\qtcreator\\cplusplus\\wrappedQtHeaders\\QtCore","-ID:\\GitTest\\Bejeweled4","-ID:\\Qt\\6.5.3\\mingw_64\\include","-ID:\\Qt\\6.5.3\\mingw_64\\include\\QtWidgets","-ID:\\Qt\\6.5.3\\mingw_64\\include\\QtMultimedia","-ID:\\Qt\\6.5.3\\mingw_64\\include\\QtGui","-ID:\\Qt\\6.5.3\\mingw_64\\include\\QtNetwork","-ID:\\Qt\\6.5.3\\mingw_64\\include\\QtSql","-ID:\\Qt\\6.5.3\\mingw_64\\include\\QtCore","-ID:\\GitTest\\Bejeweled4\\build\\Desktop_Qt_6_5_3_MinGW_64_bit-Debug\\debug","-ID:\\GitTest\\Bejeweled4\\build\\Desktop_Qt_6_5_3_MinGW_64_bit-Debug","-ID:\\Qt\\6.5.3\\mingw_64\\mkspecs\\win32-g++","-isystem","D:\\Qt\\Tools\\mingw1120_64\\lib\\gcc\\x86_64-w64-mingw32\\11.2.0\\include\\c++","-isystem","D:\\Qt\\Tools\\mingw1120_64\\lib\\gcc\\x86_64-w64-mingw32\\11.2.0\\include\\c++\\x86_64-w64-mingw32","-isystem","D:\\Qt\\Tools\\mingw1120_64\\lib\\gcc\\x86_64-w64-mingw32\\11.2.0\\include\\c++\\backward","-isystem","D:\\Qt\\Tools\\QtCreator\\bin\\clang\\lib\\clang\\18\\include","-isystem","D:\\Qt\\Tools\\mingw1120_64\\x86_64-w64-mingw32\\include","-fmessage-length=0","-fdiagnostics-show-note-include-stack","-fretain-comments-from-system-headers","-fmacro-backtrace-limit=0","-ferror-limit=1000","-x","c++-header","D:\\GitTest\\Bejeweled4\\stonelabel.h"],"directory":"D:/GitTest/Bejeweled4/build/Desktop_Qt_6_5_3_MinGW_64_bit-Debug/.qtc_clangd","file":"D:/GitTest/Bejeweled4/stonelabel.h"},{"arguments":["clang","-Wno-documentation-unknown-command","-Wno-unknown-warning-option","-Wno-unknown-pragmas","-nostdinc","-nostdinc++","-g","-std=gnu++1z","-Wall","-Wextra","-Wextra","-fexceptions","-mthreads","-fsyntax-only","-m64","--target=x86_64-w64-mingw32","-DUNICODE","-D_UNICODE","-DWIN32","-DMINGW_HAS_SECURE_API","-DQT_QML_DEBUG","-DQT_WIDGETS_LIB","-DQT_MULTIMEDIA_LIB","-DQT_GUI_LIB","-DQT_NETWORK_LIB","-DQT_SQL_LIB","-DQT_CORE_LIB","-DQT_NEEDS_QMAIN","-DQ_CREATOR_RUN","-DQT_ANNOTATE_FUNCTION(x)=__attribute__((annotate(#x)))","-ID:\\Qt\\Tools\\QtCreator\\share\\qtcreator\\cplusplus\\wrappedMingwHeaders","-ID:\\Qt\\Tools\\QtCreator\\share\\qtcreator\\cplusplus\\wrappedQtHeaders","-ID:\\Qt\\Tools\\QtCreator\\share\\qtcreator\\cplusplus\\wrappedQtHeaders\\QtCore","-ID:\\GitTest\\Bejeweled4","-ID:\\Qt\\6.5.3\\mingw_64\\include","-ID:\\Qt\\6.5.3\\mingw_64\\include\\QtWidgets","-ID:\\Qt\\6.5.3\\mingw_64\\include\\QtMultimedia","-ID:\\Qt\\6.5.3\\mingw_64\\include\\QtGui","-ID:\\Qt\\6.5.3\\mingw_64\\include\\QtNetwork","-ID:\\Qt\\6.5.3\\mingw_64\\include\\QtSql","-ID:\\Qt\\6.5.3\\mingw_64\\include\\QtCore","-ID:\\GitTest\\Bejeweled4\\build\\Desktop_Qt_6_5_3_MinGW_64_bit-Debug\\debug","-ID:\\GitTest\\Bejeweled4\\build\\Desktop_Qt_6_5_3_MinGW_64_bit-Debug","-ID:\\Qt\\6.5.3\\mingw_64\\mkspecs\\win32-g++","-isystem","D:\\Qt\\Tools\\mingw1120_64\\lib\\gcc\\x86_64-w64-mingw32\\11.2.0\\include\\c++","-isystem","D:\\Qt\\Tools\\mingw1120_64\\lib\\gcc\\x86_64-w64-mingw32\\11.2.0\\include\\c++\\x86_64-w64-mingw32","-isystem","D:\\Qt\\Tools\\mingw1120_64\\lib\\gcc\\x86_64-w64-mingw32\\11.2.0\\include\\c++\\backward","-isystem","D:\\Qt\\Tools\\QtCreator\\bin\\clang\\lib\\clang\\18\\include","-isystem","D:\\Qt\\Tools\\mingw1120_64\\x86_64-w64-mingw32\\include","-fmessage-length=0","-fdiagnostics-show-note-include-stack","-fretain-comments-from-system-headers","-fmacro-backtrace-limit=0","-ferror-limit=1000","-x","c++-header","D:\\GitTest\\Bejeweled4\\utils.h"],"directory":"D:/GitTest/Bejeweled4/build/Desktop_Qt_6_5_3_MinGW_64_bit-Debug/.qtc_clangd","file":"D:/GitTest/Bejeweled4/utils.h"},{"arguments":["clang","-Wno-documentation-unknown-command","-Wno-unknown-warning-option","-Wno-unknown-pragmas","-nostdinc","-nostdinc++","-g","-std=gnu++1z","-Wall","-Wextra","-Wextra","-fexceptions","-mthreads","-fsyntax-only","-m64","--target=x86_64-w64-mingw32","-DUNICODE","-D_UNICODE","-DWIN32","-DMINGW_HAS_SECURE_API","-DQT_QML_DEBUG","-DQT_WIDGETS_LIB","-DQT_MULTIMEDIA_LIB","-DQT_GUI_LIB","-DQT_NETWORK_LIB","-DQT_SQL_LIB","-DQT_CORE_LIB","-DQT_NEEDS_QMAIN","-DQ_CREATOR_RUN","-DQT_ANNOTATE_FUNCTION(x)=__attribute__((annotate(#x)))","-ID:\\Qt\\Tools\\QtCreator\\share\\qtcreator\\cplusplus\\wrappedMingwHeaders","-ID:\\Qt\\Tools\\QtCreator\\share\\qtcreator\\cplusplus\\wrappedQtHeaders","-ID:\\Qt\\Tools\\QtCreator\\share\\qtcreator\\cplusplus\\wrappedQtHeaders\\QtCore","-ID:\\GitTest\\Bejeweled4","-ID:\\Qt\\6.5.3\\mingw_64\\include","-ID:\\Qt\\6.5.3\\mingw_64\\include\\QtWidgets","-ID:\\Qt\\6.5.3\\mingw_64\\include\\QtMultimedia","-ID:\\Qt\\6.5.3\\mingw_64\\include\\QtGui","-ID:\\Qt\\6.5.3\\mingw_64\\include\\QtNetwork","-ID:\\Qt\\6.5.3\\mingw_64\\include\\QtSql","-ID:\\Qt\\6.5.3\\mingw_64\\include\\QtCore","-ID:\\GitTest\\Bejeweled4\\build\\Desktop_Qt_6_5_3_MinGW_64_bit-Debug\\debug","-ID:\\GitTest\\Bejeweled4\\build\\Desktop_Qt_6_5_3_MinGW_64_bit-Debug","-ID:\\Qt\\6.5.3\\mingw_64\\mkspecs\\win32-g++","-isystem","D:\\Qt\\Tools\\mingw1120_64\\lib\\gcc\\x86_64-w64-mingw32\\11.2.0\\include\\c++","-isystem","D:\\Qt\\Tools\\mingw1120_64\\lib\\gcc\\x86_64-w64-mingw32\\11.2.0\\include\\c++\\x86_64-w64-mingw32","-isystem","D:\\Qt\\Tools\\mingw1120_64\\lib\\gcc\\x86_64-w64-mingw32\\11.2.0\\include\\c++\\backward","-isystem","D:\\Qt\\Tools\\QtCreator\\bin\\clang\\lib\\clang\\18\\include","-isystem","D:\\Qt\\Tools\\mingw1120_64\\x86_64-w64-mingw32\\include","-fmessage-length=0","-fdiagnostics-show-note-include-stack","-fretain-comments-from-system-headers","-fmacro-backtrace-limit=0","-ferror-limit=1000","-x","c++-header","D:\\GitTest\\Bejeweled4\\build\\Desktop_Qt_6_5_3_MinGW_64_bit-Debug\\ui_shopwidget.h"],"directory":"D:/GitTest/Bejeweled4/build/Desktop_Qt_6_5_3_MinGW_64_bit-Debug/.qtc_clangd","file":"D:/GitTest/Bejeweled4/build/Desktop_Qt_6_5_3_MinGW_64_bit-Debug/ui_shopwidget.h"},{"arguments":["clang","-Wno-documentation-unknown-command","-Wno-unknown-warning-option","-Wno-unknown-pragmas","-nostdinc","-nostdinc++","-g","-std=gnu++1z","-Wall","-Wextra","-Wextra","-fexceptions","-mthreads","-fsyntax-only","-m64","--target=x86_64-w64-mingw32","-DUNICODE","-D_UNICODE","-DWIN32","-DMINGW_HAS_SECURE_API","-DQT_QML_DEBUG","-DQT_WIDGETS_LIB","-DQT_MULTIMEDIA_LIB","-DQT_GUI_LIB","-DQT_NETWORK_LIB","-DQT_SQL_LIB","-DQT_CORE_LIB","-DQT_NEEDS_QMAIN","-DQ_CREATOR_RUN","-DQT_ANNOTATE_FUNCTION(x)=__attribute__((annotate(#x)))","-ID:\\Qt\\Tools\\QtCreator\\share\\qtcreator\\cplusplus\\wrappedMingwHeaders","-ID:\\Qt\\Tools\\QtCreator\\share\\qtcreator\\cplusplus\\wrappedQtHeaders","-ID:\\Qt\\Tools\\QtCreator\\share\\qtcreator\\cplusplus\\wrappedQtHeaders\\QtCore","-ID:\\GitTest\\Bejeweled4","-ID:\\Qt\\6.5.3\\mingw_64\\include","-ID:\\Qt\\6.5.3\\mingw_64\\include\\QtWidgets","-ID:\\Qt\\6.5.3\\mingw_64\\include\\QtMultimedia","-ID:\\Qt\\6.5.3\\mingw_64\\include\\QtGui","-ID:\\Qt\\6.5.3\\mingw_64\\include\\QtNetwork","-ID:\\Qt\\6.5.3\\mingw_64\\include\\QtSql","-ID:\\Qt\\6.5.3\\mingw_64\\include\\QtCore","-ID:\\GitTest\\Bejeweled4\\build\\Desktop_Qt_6_5_3_MinGW_64_bit-Debug\\debug","-ID:\\GitTest\\Bejeweled4\\build\\Desktop_Qt_6_5_3_MinGW_64_bit-Debug","-ID:\\Qt\\6.5.3\\mingw_64\\mkspecs\\win32-g++","-isystem","D:\\Qt\\Tools\\mingw1120_64\\lib\\gcc\\x86_64-w64-mingw32\\11.2.0\\include\\c++","-isystem","D:\\Qt\\Tools\\mingw1120_64\\lib\\gcc\\x86_64-w64-mingw32\\11.2.0\\include\\c++\\x86_64-w64-mingw32","-isystem","D:\\Qt\\Tools\\mingw1120_64\\lib\\gcc\\x86_64-w64-mingw32\\11.2.0\\include\\c++\\backward","-isystem","D:\\Qt\\Tools\\QtCreator\\bin\\clang\\lib\\clang\\18\\include","-isystem","D:\\Qt\\Tools\\mingw1120_64\\x86_64-w64-mingw32\\include","-fmessage-length=0","-fdiagnostics-show-note-include-stack","-fretain-comments-from-system-headers","-fmacro-backtrace-limit=0","-ferror-limit=1000","-x","c++-header","D:\\GitTest\\Bejeweled4\\build\\Desktop_Qt_6_5_3_MinGW_64_bit-Debug\\ui_mainwindow.h"],"directory":"D:/GitTest/Bejeweled4/build/Desktop_Qt_6_5_3_MinGW_64_bit-Debug/.qtc_clangd","file":"D:/GitTest/Bejeweled4/build/Desktop_Qt_6_5_3_MinGW_64_bit-Debug/ui_mainwindow.h"},{"arguments":["clang","-Wno-documentation-unknown-command","-Wno-unknown-warning-option","-Wno-unknown-pragmas","-nostdinc","-nostdinc++","-g","-std=gnu++1z","-Wall","-Wextra","-Wextra","-fexceptions","-mthreads","-fsyntax-only","-m64","--target=x86_64-w64-mingw32","-DUNICODE","-D_UNICODE","-DWIN32","-DMINGW_HAS_SECURE_API","-DQT_QML_DEBUG","-DQT_WIDGETS_LIB","-DQT_MULTIMEDIA_LIB","-DQT_GUI_LIB","-DQT_NETWORK_LIB","-DQT_SQL_LIB","-DQT_CORE_LIB","-DQT_NEEDS_QMAIN","-DQ_CREATOR_RUN","-DQT_ANNOTATE_FUNCTION(x)=__attribute__((annotate(#x)))","-ID:\\Qt\\Tools\\QtCreator\\share\\qtcreator\\cplusplus\\wrappedMingwHeaders","-ID:\\Qt\\Tools\\QtCreator\\share\\qtcreator\\cplusplus\\wrappedQtHeaders","-ID:\\Qt\\Tools\\QtCreator\\share\\qtcreator\\cplusplus\\wrappedQtHeaders\\QtCore","-ID:\\GitTest\\Bejeweled4","-ID:\\Qt\\6.5.3\\mingw_64\\include","-ID:\\Qt\\6.5.3\\mingw_64\\include\\QtWidgets","-ID:\\Qt\\6.5.3\\mingw_64\\include\\QtMultimedia","-ID:\\Qt\\6.5.3\\mingw_64\\include\\QtGui","-ID:\\Qt\\6.5.3\\mingw_64\\include\\QtNetwork","-ID:\\Qt\\6.5.3\\mingw_64\\include\\QtSql","-ID:\\Qt\\6.5.3\\mingw_64\\include\\QtCore","-ID:\\GitTest\\Bejeweled4\\build\\Desktop_Qt_6_5_3_MinGW_64_bit-Debug\\debug","-ID:\\GitTest\\Bejeweled4\\build\\Desktop_Qt_6_5_3_MinGW_64_bit-Debug","-ID:\\Qt\\6.5.3\\mingw_64\\mkspecs\\win32-g++","-isystem","D:\\Qt\\Tools\\mingw1120_64\\lib\\gcc\\x86_64-w64-mingw32\\11.2.0\\include\\c++","-isystem","D:\\Qt\\Tools\\mingw1120_64\\lib\\gcc\\x86_64-w64-mingw32\\11.2.0\\include\\c++\\x86_64-w64-mingw32","-isystem","D:\\Qt\\Tools\\mingw1120_64\\lib\\gcc\\x86_64-w64-mingw32\\11.2.0\\include\\c++\\backward","-isystem","D:\\Qt\\Tools\\QtCreator\\bin\\clang\\lib\\clang\\18\\include","-isystem","D:\\Qt\\Tools\\mingw1120_64\\x86_64-w64-mingw32\\include","-fmessage-length=0","-fdiagnostics-show-note-include-stack","-fretain-comments-from-system-headers","-fmacro-backtrace-limit=0","-ferror-limit=1000","-x","c++-header","D:\\GitTest\\Bejeweled4\\build\\Desktop_Qt_6_5_3_MinGW_64_bit-Debug\\ui_end.h"],"directory":"D:/GitTest/Bejeweled4/build/Desktop_Qt_6_5_3_MinGW_64_bit-Debug/.qtc_clangd","file":"D:/GitTest/Bejeweled4/build/Desktop_Qt_6_5_3_MinGW_64_bit-Debug/ui_end.h"},{"arguments":["clang","-Wno-documentation-unknown-command","-Wno-unknown-warning-option","-Wno-unknown-pragmas","-nostdinc","-nostdinc++","-g","-std=gnu++1z","-Wall","-Wextra","-Wextra","-fexceptions","-mthreads","-fsyntax-only","-m64","--target=x86_64-w64-mingw32","-DUNICODE","-D_UNICODE","-DWIN32","-DMINGW_HAS_SECURE_API","-DQT_QML_DEBUG","-DQT_WIDGETS_LIB","-DQT_MULTIMEDIA_LIB","-DQT_GUI_LIB","-DQT_NETWORK_LIB","-DQT_SQL_LIB","-DQT_CORE_LIB","-DQT_NEEDS_QMAIN","-DQ_CREATOR_RUN","-DQT_ANNOTATE_FUNCTION(x)=__attribute__((annotate(#x)))","-ID:\\Qt\\Tools\\QtCreator\\share\\qtcreator\\cplusplus\\wrappedMingwHeaders","-ID:\\Qt\\Tools\\QtCreator\\share\\qtcreator\\cplusplus\\wrappedQtHeaders","-ID:\\Qt\\Tools\\QtCreator\\share\\qtcreator\\cplusplus\\wrappedQtHeaders\\QtCore","-ID:\\GitTest\\Bejeweled4","-ID:\\Qt\\6.5.3\\mingw_64\\include","-ID:\\Qt\\6.5.3\\mingw_64\\include\\QtWidgets","-ID:\\Qt\\6.5.3\\mingw_64\\include\\QtMultimedia","-ID:\\Qt\\6.5.3\\mingw_64\\include\\QtGui","-ID:\\Qt\\6.5.3\\mingw_64\\include\\QtNetwork","-ID:\\Qt\\6.5.3\\mingw_64\\include\\QtSql","-ID:\\Qt\\6.5.3\\mingw_64\\include\\QtCore","-ID:\\GitTest\\Bejeweled4\\build\\Desktop_Qt_6_5_3_MinGW_64_bit-Debug\\debug","-ID:\\GitTest\\Bejeweled4\\build\\Desktop_Qt_6_5_3_MinGW_64_bit-Debug","-ID:\\Qt\\6.5.3\\mingw_64\\mkspecs\\win32-g++","-isystem","D:\\Qt\\Tools\\mingw1120_64\\lib\\gcc\\x86_64-w64-mingw32\\11.2.0\\include\\c++","-isystem","D:\\Qt\\Tools\\mingw1120_64\\lib\\gcc\\x86_64-w64-mingw32\\11.2.0\\include\\c++\\x86_64-w64-mingw32","-isystem","D:\\Qt\\Tools\\mingw1120_64\\lib\\gcc\\x86_64-w64-mingw32\\11.2.0\\include\\c++\\backward","-isystem","D:\\Qt\\Tools\\QtCreator\\bin\\clang\\lib\\clang\\18\\include","-isystem","D:\\Qt\\Tools\\mingw1120_64\\x86_64-w64-mingw32\\include","-fmessage-length=0","-fdiagnostics-show-note-include-stack","-fretain-comments-from-system-headers","-fmacro-backtrace-limit=0","-ferror-limit=1000","-x","c++-header","D:\\GitTest\\Bejeweled4\\build\\Desktop_Qt_6_5_3_MinGW_64_bit-Debug\\ui_client.h"],"directory":"D:/GitTest/Bejeweled4/build/Desktop_Qt_6_5_3_MinGW_64_bit-Debug/.qtc_clangd","file":"D:/GitTest/Bejeweled4/build/Desktop_Qt_6_5_3_MinGW_64_bit-Debug/ui_client.h"},{"arguments":["clang","-Wno-documentation-unknown-command","-Wno-unknown-warning-option","-Wno-unknown-pragmas","-nostdinc","-nostdinc++","-g","-std=gnu++1z","-Wall","-Wextra","-Wextra","-fexceptions","-mthreads","-fsyntax-only","-m64","--target=x86_64-w64-mingw32","-DUNICODE","-D_UNICODE","-DWIN32","-DMINGW_HAS_SECURE_API","-DQT_QML_DEBUG","-DQT_WIDGETS_LIB","-DQT_MULTIMEDIA_LIB","-DQT_GUI_LIB","-DQT_NETWORK_LIB","-DQT_SQL_LIB","-DQT_CORE_LIB","-DQT_NEEDS_QMAIN","-DQ_CREATOR_RUN","-DQT_ANNOTATE_FUNCTION(x)=__attribute__((annotate(#x)))","-ID:\\Qt\\Tools\\QtCreator\\share\\qtcreator\\cplusplus\\wrappedMingwHeaders","-ID:\\Qt\\Tools\\QtCreator\\share\\qtcreator\\cplusplus\\wrappedQtHeaders","-ID:\\Qt\\Tools\\QtCreator\\share\\qtcreator\\cplusplus\\wrappedQtHeaders\\QtCore","-ID:\\GitTest\\Bejeweled4","-ID:\\Qt\\6.5.3\\mingw_64\\include","-ID:\\Qt\\6.5.3\\mingw_64\\include\\QtWidgets","-ID:\\Qt\\6.5.3\\mingw_64\\include\\QtMultimedia","-ID:\\Qt\\6.5.3\\mingw_64\\include\\QtGui","-ID:\\Qt\\6.5.3\\mingw_64\\include\\QtNetwork","-ID:\\Qt\\6.5.3\\mingw_64\\include\\QtSql","-ID:\\Qt\\6.5.3\\mingw_64\\include\\QtCore","-ID:\\GitTest\\Bejeweled4\\build\\Desktop_Qt_6_5_3_MinGW_64_bit-Debug\\debug","-ID:\\GitTest\\Bejeweled4\\build\\Desktop_Qt_6_5_3_MinGW_64_bit-Debug","-ID:\\Qt\\6.5.3\\mingw_64\\mkspecs\\win32-g++","-isystem","D:\\Qt\\Tools\\mingw1120_64\\lib\\gcc\\x86_64-w64-mingw32\\11.2.0\\include\\c++","-isystem","D:\\Qt\\Tools\\mingw1120_64\\lib\\gcc\\x86_64-w64-mingw32\\11.2.0\\include\\c++\\x86_64-w64-mingw32","-isystem","D:\\Qt\\Tools\\mingw1120_64\\lib\\gcc\\x86_64-w64-mingw32\\11.2.0\\include\\c++\\backward","-isystem","D:\\Qt\\Tools\\QtCreator\\bin\\clang\\lib\\clang\\18\\include","-isystem","D:\\Qt\\Tools\\mingw1120_64\\x86_64-w64-mingw32\\include","-fmessage-length=0","-fdiagnostics-show-note-include-stack","-fretain-comments-from-system-headers","-fmacro-backtrace-limit=0","-ferror-limit=1000","-x","c++-header","D:\\GitTest\\Bejeweled4\\build\\Desktop_Qt_6_5_3_MinGW_64_bit-Debug\\ui_game.h"],"directory":"D:/GitTest/Bejeweled4/build/Desktop_Qt_6_5_3_MinGW_64_bit-Debug/.qtc_clangd","file":"D:/GitTest/Bejeweled4/build/Desktop_Qt_6_5_3_MinGW_64_bit-Debug/ui_game.h"},{"arguments":["clang","-Wno-documentation-unknown-command","-Wno-unknown-warning-option","-Wno-unknown-pragmas","-nostdinc","-nostdinc++","-g","-std=gnu++1z","-Wall","-Wextra","-Wextra","-fexceptions","-mthreads","-fsyntax-only","-m64","--target=x86_64-w64-mingw32","-DUNICODE","-D_UNICODE","-DWIN32","-DMINGW_HAS_SECURE_API","-DQT_QML_DEBUG","-DQT_WIDGETS_LIB","-DQT_MULTIMEDIA_LIB","-DQT_GUI_LIB","-DQT_NETWORK_LIB","-DQT_SQL_LIB","-DQT_CORE_LIB","-DQT_NEEDS_QMAIN","-DQ_CREATOR_RUN","-DQT_ANNOTATE_FUNCTION(x)=__attribute__((annotate(#x)))","-ID:\\Qt\\Tools\\QtCreator\\share\\qtcreator\\cplusplus\\wrappedMingwHeaders","-ID:\\Qt\\Tools\\QtCreator\\share\\qtcreator\\cplusplus\\wrappedQtHeaders","-ID:\\Qt\\Tools\\QtCreator\\share\\qtcreator\\cplusplus\\wrappedQtHeaders\\QtCore","-ID:\\GitTest\\Bejeweled4","-ID:\\Qt\\6.5.3\\mingw_64\\include","-ID:\\Qt\\6.5.3\\mingw_64\\include\\QtWidgets","-ID:\\Qt\\6.5.3\\mingw_64\\include\\QtMultimedia","-ID:\\Qt\\6.5.3\\mingw_64\\include\\QtGui","-ID:\\Qt\\6.5.3\\mingw_64\\include\\QtNetwork","-ID:\\Qt\\6.5.3\\mingw_64\\include\\QtSql","-ID:\\Qt\\6.5.3\\mingw_64\\include\\QtCore","-ID:\\GitTest\\Bejeweled4\\build\\Desktop_Qt_6_5_3_MinGW_64_bit-Debug\\debug","-ID:\\GitTest\\Bejeweled4\\build\\Desktop_Qt_6_5_3_MinGW_64_bit-Debug","-ID:\\Qt\\6.5.3\\mingw_64\\mkspecs\\win32-g++","-isystem","D:\\Qt\\Tools\\mingw1120_64\\lib\\gcc\\x86_64-w64-mingw32\\11.2.0\\include\\c++","-isystem","D:\\Qt\\Tools\\mingw1120_64\\lib\\gcc\\x86_64-w64-mingw32\\11.2.0\\include\\c++\\x86_64-w64-mingw32","-isystem","D:\\Qt\\Tools\\mingw1120_64\\lib\\gcc\\x86_64-w64-mingw32\\11.2.0\\include\\c++\\backward","-isystem","D:\\Qt\\Tools\\QtCreator\\bin\\clang\\lib\\clang\\18\\include","-isystem","D:\\Qt\\Tools\\mingw1120_64\\x86_64-w64-mingw32\\include","-fmessage-length=0","-fdiagnostics-show-note-include-stack","-fretain-comments-from-system-headers","-fmacro-backtrace-limit=0","-ferror-limit=1000","-x","c++-header","D:\\GitTest\\Bejeweled4\\build\\Desktop_Qt_6_5_3_MinGW_64_bit-Debug\\ui_Login.h"],"directory":"D:/GitTest/Bejeweled4/build/Desktop_Qt_6_5_3_MinGW_64_bit-Debug/.qtc_clangd","file":"D:/GitTest/Bejeweled4/build/Desktop_Qt_6_5_3_MinGW_64_bit-Debug/ui_Login.h"},{"arguments":["clang","-Wno-documentation-unknown-command","-Wno-unknown-warning-option","-Wno-unknown-pragmas","-nostdinc","-nostdinc++","-g","-std=gnu++1z","-Wall","-Wextra","-Wextra","-fexceptions","-mthreads","-fsyntax-only","-m64","--target=x86_64-w64-mingw32","-DUNICODE","-D_UNICODE","-DWIN32","-DMINGW_HAS_SECURE_API","-DQT_QML_DEBUG","-DQT_WIDGETS_LIB","-DQT_MULTIMEDIA_LIB","-DQT_GUI_LIB","-DQT_NETWORK_LIB","-DQT_SQL_LIB","-DQT_CORE_LIB","-DQT_NEEDS_QMAIN","-DQ_CREATOR_RUN","-DQT_ANNOTATE_FUNCTION(x)=__attribute__((annotate(#x)))","-ID:\\Qt\\Tools\\QtCreator\\share\\qtcreator\\cplusplus\\wrappedMingwHeaders","-ID:\\Qt\\Tools\\QtCreator\\share\\qtcreator\\cplusplus\\wrappedQtHeaders","-ID:\\Qt\\Tools\\QtCreator\\share\\qtcreator\\cplusplus\\wrappedQtHeaders\\QtCore","-ID:\\GitTest\\Bejeweled4","-ID:\\Qt\\6.5.3\\mingw_64\\include","-ID:\\Qt\\6.5.3\\mingw_64\\include\\QtWidgets","-ID:\\Qt\\6.5.3\\mingw_64\\include\\QtMultimedia","-ID:\\Qt\\6.5.3\\mingw_64\\include\\QtGui","-ID:\\Qt\\6.5.3\\mingw_64\\include\\QtNetwork","-ID:\\Qt\\6.5.3\\mingw_64\\include\\QtSql","-ID:\\Qt\\6.5.3\\mingw_64\\include\\QtCore","-ID:\\GitTest\\Bejeweled4\\build\\Desktop_Qt_6_5_3_MinGW_64_bit-Debug\\debug","-ID:\\GitTest\\Bejeweled4\\build\\Desktop_Qt_6_5_3_MinGW_64_bit-Debug","-ID:\\Qt\\6.5.3\\mingw_64\\mkspecs\\win32-g++","-isystem","D:\\Qt\\Tools\\mingw1120_64\\lib\\gcc\\x86_64-w64-mingw32\\11.2.0\\include\\c++","-isystem","D:\\Qt\\Tools\\mingw1120_64\\lib\\gcc\\x86_64-w64-mingw32\\11.2.0\\include\\c++\\x86_64-w64-mingw32","-isystem","D:\\Qt\\Tools\\mingw1120_64\\lib\\gcc\\x86_64-w64-mingw32\\11.2.0\\include\\c++\\backward","-isystem","D:\\Qt\\Tools\\QtCreator\\bin\\clang\\lib\\clang\\18\\include","-isystem","D:\\Qt\\Tools\\mingw1120_64\\x86_64-w64-mingw32\\include","-fmessage-length=0","-fdiagnostics-show-note-include-stack","-fretain-comments-from-system-headers","-fmacro-backtrace-limit=0","-ferror-limit=1000","-x","c++-header","D:\\GitTest\\Bejeweled4\\build\\Desktop_Qt_6_5_3_MinGW_64_bit-Debug\\ui_settingwidget.h"],"directory":"D:/GitTest/Bejeweled4/build/Desktop_Qt_6_5_3_MinGW_64_bit-Debug/.qtc_clangd","file":"D:/GitTest/Bejeweled4/build/Desktop_Qt_6_5_3_MinGW_64_bit-Debug/ui_settingwidget.h"},{"arguments":["clang","-Wno-documentation-unknown-command","-Wno-unknown-warning-option","-Wno-unknown-pragmas","-nostdinc","-nostdinc++","-g","-std=gnu++1z","-Wall","-Wextra","-Wextra","-fexceptions","-mthreads","-fsyntax-only","-m64","--target=x86_64-w64-mingw32","-DUNICODE","-D_UNICODE","-DWIN32","-DMINGW_HAS_SECURE_API","-DQT_QML_DEBUG","-DQT_WIDGETS_LIB","-DQT_MULTIMEDIA_LIB","-DQT_GUI_LIB","-DQT_NETWORK_LIB","-DQT_SQL_LIB","-DQT_CORE_LIB","-DQT_NEEDS_QMAIN","-DQ_CREATOR_RUN","-DQT_ANNOTATE_FUNCTION(x)=__attribute__((annotate(#x)))","-ID:\\Qt\\Tools\\QtCreator\\share\\qtcreator\\cplusplus\\wrappedMingwHeaders","-ID:\\Qt\\Tools\\QtCreator\\share\\qtcreator\\cplusplus\\wrappedQtHeaders","-ID:\\Qt\\Tools\\QtCreator\\share\\qtcreator\\cplusplus\\wrappedQtHeaders\\QtCore","-ID:\\GitTest\\Bejeweled4","-ID:\\Qt\\6.5.3\\mingw_64\\include","-ID:\\Qt\\6.5.3\\mingw_64\\include\\QtWidgets","-ID:\\Qt\\6.5.3\\mingw_64\\include\\QtMultimedia","-ID:\\Qt\\6.5.3\\mingw_64\\include\\QtGui","-ID:\\Qt\\6.5.3\\mingw_64\\include\\QtNetwork","-ID:\\Qt\\6.5.3\\mingw_64\\include\\QtSql","-ID:\\Qt\\6.5.3\\mingw_64\\include\\QtCore","-ID:\\GitTest\\Bejeweled4\\build\\Desktop_Qt_6_5_3_MinGW_64_bit-Debug\\debug","-ID:\\GitTest\\Bejeweled4\\build\\Desktop_Qt_6_5_3_MinGW_64_bit-Debug","-ID:\\Qt\\6.5.3\\mingw_64\\mkspecs\\win32-g++","-isystem","D:\\Qt\\Tools\\mingw1120_64\\lib\\gcc\\x86_64-w64-mingw32\\11.2.0\\include\\c++","-isystem","D:\\Qt\\Tools\\mingw1120_64\\lib\\gcc\\x86_64-w64-mingw32\\11.2.0\\include\\c++\\x86_64-w64-mingw32","-isystem","D:\\Qt\\Tools\\mingw1120_64\\lib\\gcc\\x86_64-w64-mingw32\\11.2.0\\include\\c++\\backward","-isystem","D:\\Qt\\Tools\\QtCreator\\bin\\clang\\lib\\clang\\18\\include","-isystem","D:\\Qt\\Tools\\mingw1120_64\\x86_64-w64-mingw32\\include","-fmessage-length=0","-fdiagnostics-show-note-include-stack","-fretain-comments-from-system-headers","-fmacro-backtrace-limit=0","-ferror-limit=1000","-x","c++-header","D:\\GitTest\\Bejeweled4\\build\\Desktop_Qt_6_5_3_MinGW_64_bit-Debug\\ui_rankdialog.h"],"directory":"D:/GitTest/Bejeweled4/build/Desktop_Qt_6_5_3_MinGW_64_bit-Debug/.qtc_clangd","file":"D:/GitTest/Bejeweled4/build/Desktop_Qt_6_5_3_MinGW_64_bit-Debug/ui_rankdialog.h"},{"arguments":["clang","-Wno-documentation-unknown-command","-Wno-unknown-warning-option","-Wno-unknown-pragmas","-nostdinc","-nostdinc++","-g","-std=gnu++1z","-Wall","-Wextra","-Wextra","-fexceptions","-mthreads","-fsyntax-only","-m64","--target=x86_64-w64-mingw32","-DUNICODE","-D_UNICODE","-DWIN32","-DMINGW_HAS_SECURE_API","-DQT_QML_DEBUG","-DQT_WIDGETS_LIB","-DQT_MULTIMEDIA_LIB","-DQT_GUI_LIB","-DQT_NETWORK_LIB","-DQT_SQL_LIB","-DQT_CORE_LIB","-DQT_NEEDS_QMAIN","-DQ_CREATOR_RUN","-DQT_ANNOTATE_FUNCTION(x)=__attribute__((annotate(#x)))","-ID:\\Qt\\Tools\\QtCreator\\share\\qtcreator\\cplusplus\\wrappedMingwHeaders","-ID:\\Qt\\Tools\\QtCreator\\share\\qtcreator\\cplusplus\\wrappedQtHeaders","-ID:\\Qt\\Tools\\QtCreator\\share\\qtcreator\\cplusplus\\wrappedQtHeaders\\QtCore","-ID:\\GitTest\\Bejeweled4","-ID:\\Qt\\6.5.3\\mingw_64\\include","-ID:\\Qt\\6.5.3\\mingw_64\\include\\QtWidgets","-ID:\\Qt\\6.5.3\\mingw_64\\include\\QtMultimedia","-ID:\\Qt\\6.5.3\\mingw_64\\include\\QtGui","-ID:\\Qt\\6.5.3\\mingw_64\\include\\QtNetwork","-ID:\\Qt\\6.5.3\\mingw_64\\include\\QtSql","-ID:\\Qt\\6.5.3\\mingw_64\\include\\QtCore","-ID:\\GitTest\\Bejeweled4\\build\\Desktop_Qt_6_5_3_MinGW_64_bit-Debug\\debug","-ID:\\GitTest\\Bejeweled4\\build\\Desktop_Qt_6_5_3_MinGW_64_bit-Debug","-ID:\\Qt\\6.5.3\\mingw_64\\mkspecs\\win32-g++","-isystem","D:\\Qt\\Tools\\mingw1120_64\\lib\\gcc\\x86_64-w64-mingw32\\11.2.0\\include\\c++","-isystem","D:\\Qt\\Tools\\mingw1120_64\\lib\\gcc\\x86_64-w64-mingw32\\11.2.0\\include\\c++\\x86_64-w64-mingw32","-isystem","D:\\Qt\\Tools\\mingw1120_64\\lib\\gcc\\x86_64-w64-mingw32\\11.2.0\\include\\c++\\backward","-isystem","D:\\Qt\\Tools\\QtCreator\\bin\\clang\\lib\\clang\\18\\include","-isystem","D:\\Qt\\Tools\\mingw1120_64\\x86_64-w64-mingw32\\include","-fmessage-length=0","-fdiagnostics-show-note-include-stack","-fretain-comments-from-system-headers","-fmacro-backtrace-limit=0","-ferror-limit=1000","-x","c++-header","D:\\GitTest\\Bejeweled4\\build\\Desktop_Qt_6_5_3_MinGW_64_bit-Debug\\ui_signup.h"],"directory":"D:/GitTest/Bejeweled4/build/Desktop_Qt_6_5_3_MinGW_64_bit-Debug/.qtc_clangd","file":"D:/GitTest/Bejeweled4/build/Desktop_Qt_6_5_3_MinGW_64_bit-Debug/ui_signup.h"},{"arguments":["clang","-Wno-documentation-unknown-command","-Wno-unknown-warning-option","-Wno-unknown-pragmas","-nostdinc","-nostdinc++","-g","-std=gnu++1z","-Wall","-Wextra","-Wextra","-fexceptions","-mthreads","-fsyntax-only","-m64","--target=x86_64-w64-mingw32","-DUNICODE","-D_UNICODE","-DWIN32","-DMINGW_HAS_SECURE_API","-DQT_QML_DEBUG","-DQT_WIDGETS_LIB","-DQT_MULTIMEDIA_LIB","-DQT_GUI_LIB","-DQT_NETWORK_LIB","-DQT_SQL_LIB","-DQT_CORE_LIB","-DQT_NEEDS_QMAIN","-DQ_CREATOR_RUN","-DQT_ANNOTATE_FUNCTION(x)=__attribute__((annotate(#x)))","-ID:\\Qt\\Tools\\QtCreator\\share\\qtcreator\\cplusplus\\wrappedMingwHeaders","-ID:\\Qt\\Tools\\QtCreator\\share\\qtcreator\\cplusplus\\wrappedQtHeaders","-ID:\\Qt\\Tools\\QtCreator\\share\\qtcreator\\cplusplus\\wrappedQtHeaders\\QtCore","-ID:\\GitTest\\Bejeweled4","-ID:\\Qt\\6.5.3\\mingw_64\\include","-ID:\\Qt\\6.5.3\\mingw_64\\include\\QtWidgets","-ID:\\Qt\\6.5.3\\mingw_64\\include\\QtMultimedia","-ID:\\Qt\\6.5.3\\mingw_64\\include\\QtGui","-ID:\\Qt\\6.5.3\\mingw_64\\include\\QtNetwork","-ID:\\Qt\\6.5.3\\mingw_64\\include\\QtSql","-ID:\\Qt\\6.5.3\\mingw_64\\include\\QtCore","-ID:\\GitTest\\Bejeweled4\\build\\Desktop_Qt_6_5_3_MinGW_64_bit-Debug\\debug","-ID:\\GitTest\\Bejeweled4\\build\\Desktop_Qt_6_5_3_MinGW_64_bit-Debug","-ID:\\Qt\\6.5.3\\mingw_64\\mkspecs\\win32-g++","-isystem","D:\\Qt\\Tools\\mingw1120_64\\lib\\gcc\\x86_64-w64-mingw32\\11.2.0\\include\\c++","-isystem","D:\\Qt\\Tools\\mingw1120_64\\lib\\gcc\\x86_64-w64-mingw32\\11.2.0\\include\\c++\\x86_64-w64-mingw32","-isystem","D:\\Qt\\Tools\\mingw1120_64\\lib\\gcc\\x86_64-w64-mingw32\\11.2.0\\include\\c++\\backward","-isystem","D:\\Qt\\Tools\\QtCreator\\bin\\clang\\lib\\clang\\18\\include","-isystem","D:\\Qt\\Tools\\mingw1120_64\\x86_64-w64-mingw32\\include","-fmessage-length=0","-fdiagnostics-show-note-include-stack","-fretain-comments-from-system-headers","-fmacro-backtrace-limit=0","-ferror-limit=1000","-x","c++-header","D:\\GitTest\\Bejeweled4\\build\\Desktop_Qt_6_5_3_MinGW_64_bit-Debug\\ui_pause.h"],"directory":"D:/GitTest/Bejeweled4/build/Desktop_Qt_6_5_3_MinGW_64_bit-Debug/.qtc_clangd","file":"D:/GitTest/Bejeweled4/build/Desktop_Qt_6_5_3_MinGW_64_bit-Debug/ui_pause.h"}]